{"_schema":"lxx-chapter-v1","edition":"Prov","chapter":34,"sourceFile":"lxx_rahlfs_1935_Prov.json","parentMeta":{"source":"LXX Rahlfs 1935","license":"CC BY-NC-SA","schema":"lxx-word-morph-v1"},"verses":{"1":[{"w":"μὴ","lemma":"μή","morph":"D"},{"w":"καυχῶ","lemma":"καυχάομαι","morph":"V.PMD2S"},{"w":"τὰ","lemma":"ὁ","morph":"RA.APN"},{"w":"εἰς","lemma":"εἰς","morph":"P"},{"w":"αὔριον","lemma":"αὔριον","morph":"D"},{"w":"οὐ","lemma":"οὐ","morph":"D"},{"w":"γὰρ","lemma":"γάρ","morph":"X"},{"w":"γινώσκεις","lemma":"γινώσκω","morph":"V.PAI2S"},{"w":"τί","lemma":"τίς","morph":"RI.ASN"},{"w":"τέξεται","lemma":"τίκτω","morph":"V.FMI3S"},{"w":"ἡ","lemma":"ὁ","morph":"RA.NSF"},{"w":"ἐπιοῦσα","lemma":"ἔπειμι","morph":"V.PAPNSF"}],"2":[{"w":"ἐγκωμιαζέτω","lemma":"ἐγκωμιάζω","morph":"V.PAD3S"},{"w":"σε","lemma":"σέ","morph":"RP.AS"},{"w":"ὁ","lemma":"ὁ","morph":"RA.NSM"},{"w":"πέλας","lemma":"πέλας","morph":"D"},{"w":"καὶ","lemma":"καί","morph":"C"},{"w":"μὴ","lemma":"μή","morph":"D"},{"w":"τὸ","lemma":"ὁ","morph":"RA.NSN"},{"w":"σὸν","lemma":"σός","morph":"A.NSN"},{"w":"στόμα","lemma":"στόμα","morph":"N.NSN"},{"w":"ἀλλότριος","lemma":"ἀλλότριος","morph":"A.NSM"},{"w":"καὶ","lemma":"καί","morph":"C"},{"w":"μὴ","lemma":"μή","morph":"D"},{"w":"τὰ","lemma":"ὁ","morph":"RA.NPN"},{"w":"σὰ","lemma":"σός","morph":"A.NPN"},{"w":"χείλη","lemma":"χεῖλος","morph":"N.NPN"}],"3":[{"w":"βαρὺ","lemma":"βαρύς","morph":"A.NSN"},{"w":"λίθος","lemma":"λίθος","morph":"N.NSM"},{"w":"καὶ","lemma":"καί","morph":"C"},{"w":"δυσβάστακτον","lemma":"δυσβάστακτος","morph":"A.NSN"},{"w":"ἄμμος","lemma":"ἄμμος","morph":"N.NSF"},{"w":"ὀργὴ","lemma":"ὀργή","morph":"N.NSF"},{"w":"δὲ","lemma":"δέ","morph":"X"},{"w":"ἄφρονος","lemma":"ἄφρων","morph":"A.GSM"},{"w":"βαρυτέρα","lemma":"βαρύς","morph":"A.APNC"},{"w":"ἀμφοτέρων","lemma":"ἀμφότερος","morph":"A.GPM"}],"4":[{"w":"ἀνελεήμων","lemma":"ἀνελεήμων","morph":"A.NSM"},{"w":"θυμὸς","lemma":"θυμός","morph":"N.NSM"},{"w":"καὶ","lemma":"καί","morph":"C"},{"w":"ὀξεῖα","lemma":"ὀξύς","morph":"A.NSF"},{"w":"ὀργή","lemma":"ὀργή","morph":"N.NSF"},{"w":"ἀλλ᾿","lemma":"ἀλλά","morph":"C"},{"w":"οὐδένα","lemma":"οὐδείς","morph":"A.ASM"},{"w":"ὑφίσταται","lemma":"ὑφίστημι","morph":"V.PMI3S"},{"w":"ζῆλος","lemma":"ζῆλος","morph":"N.NSM"}],"5":[{"w":"κρείσσους","lemma":"κρείσσων","morph":"A.NPM"},{"w":"ἔλεγχοι","lemma":"ἔλεγχος","morph":"N.NPM"},{"w":"ἀποκεκαλυμμένοι","lemma":"ἀποκαλύπτω","morph":"V.XMPNPM"},{"w":"κρυπτομένης","lemma":"κρύπτω","morph":"V.PMPGSF"},{"w":"φιλίας","lemma":"φιλία","morph":"N.GSF"}],"6":[{"w":"ἀξιοπιστότερά","lemma":"ἀξιόπιστος","morph":"A.NPNC"},{"w":"ἐστιν","lemma":"εἰμί","morph":"V.PAI3S"},{"w":"τραύματα","lemma":"τραῦμα","morph":"N.NPN"},{"w":"φίλου","lemma":"φίλος","morph":"A.GSM"},{"w":"ἢ","lemma":"ἤ","morph":"C"},{"w":"ἑκούσια","lemma":"ἑκούσιος","morph":"A.NPN"},{"w":"φιλήματα","lemma":"φίλημα","morph":"N.NPN"},{"w":"ἐχθροῦ","lemma":"ἐχθρός","morph":"A.GSM"}],"7":[{"w":"ψυχὴ","lemma":"ψυχή","morph":"N.NSF"},{"w":"ἐν","lemma":"ἐν","morph":"P"},{"w":"πλησμονῇ","lemma":"πλησμονή","morph":"N.DSF"},{"w":"οὖσα","lemma":"εἰμί","morph":"V.PAPNSF"},{"w":"κηρίοις","lemma":"κηρίον","morph":"N.DPN"},{"w":"ἐμπαίζει","lemma":"ἐμπαίζω","morph":"V.PAI3S"},{"w":"ψυχῇ","lemma":"ψυχή","morph":"N.DSF"},{"w":"δὲ","lemma":"δέ","morph":"X"},{"w":"ἐνδεεῖ","lemma":"ἐνδεής","morph":"A.DSF"},{"w":"καὶ","lemma":"καί","morph":"C"},{"w":"τὰ","lemma":"ὁ","morph":"RA.NPN"},{"w":"πικρὰ","lemma":"πικρός","morph":"A.NPN"},{"w":"γλυκεῖα","lemma":"γλυκύς","morph":"A.NSF"},{"w":"φαίνεται","lemma":"φαίνω","morph":"V.PMI3S"}],"8":[{"w":"ὥσπερ","lemma":"ὥσπερ","morph":"D"},{"w":"ὅταν","lemma":"ὅταν","morph":"D"},{"w":"ὄρνεον","lemma":"ὄρνεον","morph":"N.NSN"},{"w":"καταπετασθῇ","lemma":"καταπετάννυμι","morph":"V.APS3S"},{"w":"ἐκ","lemma":"ἐκ","morph":"P"},{"w":"τῆς","lemma":"ὁ","morph":"RA.GSF"},{"w":"ἰδίας","lemma":"ἴδιος","morph":"A.GSF"},{"w":"νοσσιᾶς","lemma":"νοσσιά","morph":"N.GSF"},{"w":"οὕτως","lemma":"οὕτως","morph":"D"},{"w":"ἄνθρωπος","lemma":"ἄνθρωπος","morph":"N.NSM"},{"w":"δουλοῦται","lemma":"δουλόω","morph":"V.PMI3S"},{"w":"ὅταν","lemma":"ὅταν","morph":"D"},{"w":"ἀποξενωθῇ","lemma":"ἀποξενόω","morph":"V.APS3S"},{"w":"ἐκ","lemma":"ἐκ","morph":"P"},{"w":"τῶν","lemma":"ὁ","morph":"RA.GPM"},{"w":"ἰδίων","lemma":"ἴδιος","morph":"A.GPM"},{"w":"τόπων","lemma":"τόπος","morph":"N.GPM"}],"9":[{"w":"μύροις","lemma":"μύρον","morph":"N.DPN"},{"w":"καὶ","lemma":"καί","morph":"C"},{"w":"οἴνοις","lemma":"οἶνος","morph":"N.DPM"},{"w":"καὶ","lemma":"καί","morph":"C"},{"w":"θυμιάμασιν","lemma":"θυμίαμα","morph":"N.DPN"},{"w":"τέρπεται","lemma":"τέρπω","morph":"V.PMI3S"},{"w":"καρδία","lemma":"καρδία","morph":"N.NSF"},{"w":"καταρρήγνυται","lemma":"καταρρήγνυμι","morph":"V.PMI3S"},{"w":"δὲ","lemma":"δέ","morph":"X"},{"w":"ὑπὸ","lemma":"ὑπό","morph":"P"},{"w":"συμπτωμάτων","lemma":"σύμπτωμα","morph":"N.GPN"},{"w":"ψυχή","lemma":"ψυχή","morph":"N.NSF"}],"10":[{"w":"φίλον","lemma":"φίλος","morph":"A.ASM"},{"w":"σὸν","lemma":"σός","morph":"A.ASM"},{"w":"ἢ","lemma":"ἤ","morph":"C"},{"w":"φίλον","lemma":"φίλος","morph":"A.ASM"},{"w":"πατρῷον","lemma":"πατρῷος","morph":"A.ASM"},{"w":"μὴ","lemma":"μή","morph":"D"},{"w":"ἐγκαταλίπῃς","lemma":"ἐγκαταλείπω","morph":"V.AAS2S"},{"w":"εἰς","lemma":"εἰς","morph":"P"},{"w":"δὲ","lemma":"δέ","morph":"X"},{"w":"τὸν","lemma":"ὁ","morph":"RA.ASM"},{"w":"οἶκον","lemma":"οἶκος","morph":"N.ASM"},{"w":"τοῦ","lemma":"ὁ","morph":"RA.GSM"},{"w":"ἀδελφοῦ","lemma":"ἀδελφός","morph":"N.GSM"},{"w":"σου","lemma":"σοῦ","morph":"RP.GS"},{"w":"μὴ","lemma":"μή","morph":"D"},{"w":"εἰσέλθῃς","lemma":"εἰσέρχομαι","morph":"V.AAS2S"},{"w":"ἀτυχῶν","lemma":"ἀτυχέω","morph":"V.PAPNSM"},{"w":"κρείσσων","lemma":"κρείσσων","morph":"A.NSM"},{"w":"φίλος","lemma":"φίλος","morph":"A.NSM"},{"w":"ἐγγὺς","lemma":"ἐγγύς","morph":"D"},{"w":"ἢ","lemma":"ἤ","morph":"C"},{"w":"ἀδελφὸς","lemma":"ἀδελφός","morph":"N.NSM"},{"w":"μακρὰν","lemma":"μακράν","morph":"D"},{"w":"οἰκῶν","lemma":"οἶκος","morph":"N.GPM"}],"11":[{"w":"σοφὸς","lemma":"σοφός","morph":"A.NSM"},{"w":"γίνου","lemma":"γίνομαι","morph":"V.PMD2S"},{"w":"υἱέ","lemma":"υἱός","morph":"N.VSM"},{"w":"ἵνα","lemma":"ἵνα","morph":"C"},{"w":"εὐφραίνηταί","lemma":"εὐφραίνω","morph":"V.PMS3S"},{"w":"μου","lemma":"μου","morph":"RP.GS"},{"w":"ἡ","lemma":"ὁ","morph":"RA.NSF"},{"w":"καρδία","lemma":"καρδία","morph":"N.NSF"},{"w":"καὶ","lemma":"καί","morph":"C"},{"w":"ἀπόστρεψον","lemma":"ἀποστρέφω","morph":"V.AAD2S"},{"w":"ἀπὸ","lemma":"ἀπό","morph":"P"},{"w":"σοῦ","lemma":"σοῦ","morph":"RP.GS"},{"w":"ἐπονειδίστους","lemma":"ἐπονείδιστος","morph":"A.APM"},{"w":"λόγους","lemma":"λόγος","morph":"N.APM"}],"12":[{"w":"πανοῦργος","lemma":"πανοῦργος","morph":"A.NSM"},{"w":"κακῶν","lemma":"κακός","morph":"A.GPM"},{"w":"ἐπερχομένων","lemma":"ἐπέρχομαι","morph":"V.PMPGPM"},{"w":"ἀπεκρύβη","lemma":"ἀποκρύπτω","morph":"V.API3S"},{"w":"ἄφρονες","lemma":"ἄφρων","morph":"A.NPM"},{"w":"δὲ","lemma":"δέ","morph":"X"},{"w":"ἐπελθόντες","lemma":"ἐπέρχομαι","morph":"V.AAPNPM"},{"w":"ζημίαν","lemma":"ζημία","morph":"N.ASF"},{"w":"τείσουσιν","lemma":"τίνω","morph":"V.FAI3P"}],"13":[{"w":"ἀφελοῦ","lemma":"ἀφαιρέω","morph":"V.AMD2S"},{"w":"τὸ","lemma":"ὁ","morph":"RA.ASN"},{"w":"ἱμάτιον","lemma":"ἱμάτιον","morph":"N.ASN"},{"w":"αὐτοῦ","lemma":"αὐτός","morph":"RD.GSM"},{"w":"παρῆλθεν","lemma":"παρέρχομαι","morph":"V.AAI3S"},{"w":"γάρ","lemma":"γάρ","morph":"X"},{"w":"ὑβριστὴς","lemma":"ὑβριστής","morph":"N.NSM"},{"w":"ὅστις","lemma":"ὅστις","morph":"RX.NSM"},{"w":"τὰ","lemma":"ὁ","morph":"RA.APN"},{"w":"ἀλλότρια","lemma":"ἀλλότριος","morph":"A.APN"},{"w":"λυμαίνεται","lemma":"λυμαίνομαι","morph":"V.PMI3S"}],"14":[{"w":"ὃς","lemma":"ὅς","morph":"RR.NSM"},{"w":"ἂν","lemma":"ἄν","morph":"X"},{"w":"εὐλογῇ","lemma":"εὐλογέω","morph":"V.PAS3S"},{"w":"φίλον","lemma":"φίλος","morph":"A.ASM"},{"w":"τὸ","lemma":"ὁ","morph":"RA.ASN"},{"w":"πρωὶ","lemma":"πρωΐ","morph":"D"},{"w":"μεγάλῃ","lemma":"μέγας","morph":"A.DSF"},{"w":"τῇ","lemma":"ὁ","morph":"RA.DSF"},{"w":"φωνῇ","lemma":"φωνή","morph":"N.DSF"},{"w":"καταρωμένου","lemma":"καταράομαι","morph":"V.PMPGSM"},{"w":"οὐδὲν","lemma":"οὐδείς","morph":"A.ASN"},{"w":"διαφέρειν","lemma":"διαφέρω","morph":"V.PAN"},{"w":"δόξει","lemma":"δοκέω","morph":"V.FAI3S"}],"15":[{"w":"σταγόνες","lemma":"σταγών","morph":"N.NPM"},{"w":"ἐκβάλλουσιν","lemma":"ἐκβάλλω","morph":"V.PAI3P"},{"w":"ἄνθρωπον","lemma":"ἄνθρωπος","morph":"N.ASM"},{"w":"ἐν","lemma":"ἐν","morph":"P"},{"w":"ἡμέρᾳ","lemma":"ἡμέρα","morph":"N.DSF"},{"w":"χειμερινῇ","lemma":"χειμερινός","morph":"A.DSF"},{"w":"ἐκ","lemma":"ἐκ","morph":"P"},{"w":"τοῦ","lemma":"ὁ","morph":"RA.GSM"},{"w":"οἴκου","lemma":"οἶκος","morph":"N.GSM"},{"w":"αὐτοῦ","lemma":"αὐτός","morph":"RD.GSM"},{"w":"ὡσαύτως","lemma":"ὡσαύτως","morph":"D"},{"w":"καὶ","lemma":"καί","morph":"C"},{"w":"γυνὴ","lemma":"γυνή","morph":"N.NSF"},{"w":"λοίδορος","lemma":"λοίδορος","morph":"A.NSF"},{"w":"ἐκ","lemma":"ἐκ","morph":"P"},{"w":"τοῦ","lemma":"ὁ","morph":"RA.GSM"},{"w":"ἰδίου","lemma":"ἴδιος","morph":"A.GSM"},{"w":"οἴκου","lemma":"οἶκος","morph":"N.GSM"}],"16":[{"w":"βορέας","lemma":"βορρᾶς","morph":"N.NSM"},{"w":"σκληρὸς","lemma":"σκληρός","morph":"A.NSM"},{"w":"ἄνεμος","lemma":"ἄνεμος","morph":"N.NSM"},{"w":"ὀνόματι","lemma":"ὄνομα","morph":"N.DSN"},{"w":"δὲ","lemma":"δέ","morph":"X"},{"w":"ἐπιδέξιος","lemma":"ἐπιδέξιος","morph":"A.NSM"},{"w":"καλεῖται","lemma":"καλέω","morph":"V.PMI3S"}],"17":[{"w":"σίδηρος","lemma":"σίδηρος","morph":"N.NSM"},{"w":"σίδηρον","lemma":"σίδηρος","morph":"N.ASM"},{"w":"ὀξύνει","lemma":"ὀξύνω","morph":"V.PAI3S"},{"w":"ἀνὴρ","lemma":"ἀνήρ","morph":"N.NSM"},{"w":"δὲ","lemma":"δέ","morph":"X"},{"w":"παροξύνει","lemma":"παροξύνω","morph":"V.PAI3S"},{"w":"πρόσωπον","lemma":"πρόσωπον","morph":"N.ASN"},{"w":"ἑταίρου","lemma":"ἑταῖρος","morph":"N.GSM"}],"18":[{"w":"ὃς","lemma":"ὅς","morph":"RR.NSM"},{"w":"φυτεύει","lemma":"φυτεύω","morph":"V.PAI3S"},{"w":"συκῆν","lemma":"συκῆ","morph":"N.ASF"},{"w":"φάγεται","lemma":"φάγω","morph":"V.FMI3S"},{"w":"τοὺς","lemma":"ὁ","morph":"RA.APM"},{"w":"καρποὺς","lemma":"καρπός","morph":"N.APM"},{"w":"αὐτῆς","lemma":"αὐτός","morph":"RD.GSF"},{"w":"ὃς","lemma":"ὅς","morph":"RR.NSM"},{"w":"δὲ","lemma":"δέ","morph":"X"},{"w":"φυλάσσει","lemma":"φυλάσσω","morph":"V.PAI3S"},{"w":"τὸν","lemma":"ὁ","morph":"RA.ASM"},{"w":"ἑαυτοῦ","lemma":"ἑαυτοῦ","morph":"RD.GSM"},{"w":"κύριον","lemma":"κύριος","morph":"N.ASM"},{"w":"τιμηθήσεται","lemma":"τιμάω","morph":"V.FPI3S"}],"19":[{"w":"ὥσπερ","lemma":"ὥσπερ","morph":"D"},{"w":"οὐχ","lemma":"οὐ","morph":"D"},{"w":"ὅμοια","lemma":"ὅμοιος","morph":"A.NPN"},{"w":"πρόσωπα","lemma":"πρόσωπον","morph":"N.NPN"},{"w":"προσώποις","lemma":"πρόσωπον","morph":"N.DPN"},{"w":"οὕτως","lemma":"οὕτως","morph":"D"},{"w":"οὐδὲ","lemma":"οὐδέ","morph":"C"},{"w":"αἱ","lemma":"ὁ","morph":"RA.NPF"},{"w":"καρδίαι","lemma":"καρδία","morph":"N.NPF"},{"w":"τῶν","lemma":"ὁ","morph":"RA.GPM"},{"w":"ἀνθρώπων","lemma":"ἄνθρωπος","morph":"N.GPM"}],"20":[{"w":"ᾅδης","lemma":"ᾅδης","morph":"N.NSM"},{"w":"καὶ","lemma":"καί","morph":"C"},{"w":"ἀπώλεια","lemma":"ἀπώλεια","morph":"N.NSF"},{"w":"οὐκ","lemma":"οὐ","morph":"D"},{"w":"ἐμπίμπλανται","lemma":"ἐμπίπλημι","morph":"V.PMI3P"},{"w":"ὡσαύτως","lemma":"ὡσαύτως","morph":"D"},{"w":"καὶ","lemma":"καί","morph":"C"},{"w":"οἱ","lemma":"ὁ","morph":"RA.NPM"},{"w":"ὀφθαλμοὶ","lemma":"ὀφθαλμός","morph":"N.NPM"},{"w":"τῶν","lemma":"ὁ","morph":"RA.GPM"},{"w":"ἀνθρώπων","lemma":"ἄνθρωπος","morph":"N.GPM"},{"w":"ἄπληστοι","lemma":"ἄπληστος","morph":"A.NPM"}],"21":[{"w":"δοκίμιον","lemma":"δοκίμιον","morph":"N.NSN"},{"w":"ἀργύρῳ","lemma":"ἄργυρος","morph":"N.DSM"},{"w":"καὶ","lemma":"καί","morph":"C"},{"w":"χρυσῷ","lemma":"χρυσός","morph":"A.DSM"},{"w":"πύρωσις","lemma":"πύρωσις","morph":"N.NSF"},{"w":"ἀνὴρ","lemma":"ἀνήρ","morph":"N.NSM"},{"w":"δὲ","lemma":"δέ","morph":"X"},{"w":"δοκιμάζεται","lemma":"δοκιμάζω","morph":"V.PMI3S"},{"w":"διὰ","lemma":"διά","morph":"P"},{"w":"στόματος","lemma":"στόμα","morph":"N.GSN"},{"w":"ἐγκωμιαζόντων","lemma":"ἐγκωμιάζω","morph":"V.PAPGPM"},{"w":"αὐτόν","lemma":"αὐτός","morph":"RD.ASM"}],"22":[{"w":"ἐὰν","lemma":"ἐάν","morph":"C"},{"w":"μαστιγοῖς","lemma":"μαστιγόω","morph":"V.PAI2S"},{"w":"ἄφρονα","lemma":"ἄφρων","morph":"A.ASM"},{"w":"ἐν","lemma":"ἐν","morph":"P"},{"w":"μέσῳ","lemma":"μέσος","morph":"A.DSN"},{"w":"συνεδρίου","lemma":"συνέδριον","morph":"N.GSN"},{"w":"ἀτιμάζων","lemma":"ἀτιμάζω","morph":"V.PAPNSM"},{"w":"οὐ","lemma":"οὐ","morph":"D"},{"w":"μὴ","lemma":"μή","morph":"D"},{"w":"περιέλῃς","lemma":"περιέρχομαι","morph":"V.APS2S"},{"w":"τὴν","lemma":"ὁ","morph":"RA.ASF"},{"w":"ἀφροσύνην","lemma":"ἀφροσύνη","morph":"N.ASF"},{"w":"αὐτοῦ","lemma":"αὐτός","morph":"RD.GSM"}],"23":[{"w":"γνωστῶς","lemma":"γνωστῶς","morph":"D"},{"w":"ἐπιγνώσῃ","lemma":"ἐπιγινώσκω","morph":"V.FMI2S"},{"w":"ψυχὰς","lemma":"ψυχή","morph":"N.APF"},{"w":"ποιμνίου","lemma":"ποίμνιον","morph":"N.GSN"},{"w":"σου","lemma":"σοῦ","morph":"RP.GS"},{"w":"καὶ","lemma":"καί","morph":"C"},{"w":"ἐπιστήσεις","lemma":"ἐφίστημι","morph":"V.FAI2S"},{"w":"καρδίαν","lemma":"καρδία","morph":"N.ASF"},{"w":"σου","lemma":"σοῦ","morph":"RP.GS"},{"w":"σαῖς","lemma":"σός","morph":"A.DPF"},{"w":"ἀγέλαις","lemma":"ἀγέλη","morph":"N.DPF"}],"24":[{"w":"ὅτι","lemma":"ὅτι","morph":"C"},{"w":"οὐ","lemma":"οὐ","morph":"D"},{"w":"τὸν","lemma":"ὁ","morph":"RA.ASM"},{"w":"αἰῶνα","lemma":"αἰών","morph":"N.ASM"},{"w":"ἀνδρὶ","lemma":"ἀνήρ","morph":"N.DSM"},{"w":"κράτος","lemma":"κράτος","morph":"N.NSN"},{"w":"καὶ","lemma":"καί","morph":"C"},{"w":"ἰσχύς","lemma":"ἰσχύς","morph":"N.NSF"},{"w":"οὐδὲ","lemma":"οὐδέ","morph":"C"},{"w":"παραδίδωσιν","lemma":"παραδίδωμι","morph":"V.PAI3S"},{"w":"ἐκ","lemma":"ἐκ","morph":"P"},{"w":"γενεᾶς","lemma":"γενεά","morph":"N.GSF"},{"w":"εἰς","lemma":"εἰς","morph":"P"},{"w":"γενεάν","lemma":"γενεά","morph":"N.ASF"}],"25":[{"w":"ἐπιμελοῦ","lemma":"ἐπιμελέομαι","morph":"V.PMD2S"},{"w":"τῶν","lemma":"ὁ","morph":"RA.GPM"},{"w":"ἐν","lemma":"ἐν","morph":"P"},{"w":"τῷ","lemma":"ὁ","morph":"RA.DSN"},{"w":"πεδίῳ","lemma":"πεδίον","morph":"N.DSN"},{"w":"χλωρῶν","lemma":"χλωρός","morph":"A.GPM"},{"w":"καὶ","lemma":"καί","morph":"C"},{"w":"κερεῖς","lemma":"κείρω","morph":"V.FAI2S"},{"w":"πόαν","lemma":"πόα","morph":"N.ASF"},{"w":"καὶ","lemma":"καί","morph":"C"},{"w":"σύναγε","lemma":"συνάγω","morph":"V.PAD2S"},{"w":"χόρτον","lemma":"χόρτος","morph":"N.ASM"},{"w":"ὀρεινόν","lemma":"ὀρεινός","morph":"A.ASM"}],"26":[{"w":"ἵνα","lemma":"ἵνα","morph":"C"},{"w":"ἔχῃς","lemma":"ἔχω","morph":"V.PAS2S"},{"w":"πρόβατα","lemma":"πρόβατον","morph":"N.APN"},{"w":"εἰς","lemma":"εἰς","morph":"P"},{"w":"ἱματισμόν","lemma":"ἱματισμός","morph":"N.ASM"},{"w":"τίμα","lemma":"τιμάω","morph":"V.PAD2S"},{"w":"πεδίον","lemma":"πεδίον","morph":"N.ASN"},{"w":"ἵνα","lemma":"ἵνα","morph":"C"},{"w":"ὦσίν","lemma":"οὖς","morph":"N.DPN"},{"w":"σοι","lemma":"σοί","morph":"RP.DS"},{"w":"ἄρνες","lemma":"ἀρήν","morph":"N.NPM"}],"27":[{"w":"υἱέ","lemma":"υἱός","morph":"N.VSM"},{"w":"παρ᾿","lemma":"παρά","morph":"P"},{"w":"ἐμοῦ","lemma":"ἐμοῦ","morph":"RP.GS"},{"w":"ἔχεις","lemma":"ἔχω","morph":"V.PAI2S"},{"w":"ῥήσεις","lemma":"ῥῆσις","morph":"N.APF"},{"w":"ἰσχυρὰς","lemma":"ἰσχυρός","morph":"A.APF"},{"w":"εἰς","lemma":"εἰς","morph":"P"},{"w":"τὴν","lemma":"ὁ","morph":"RA.ASF"},{"w":"ζωήν","lemma":"ζωή","morph":"N.ASF"},{"w":"σου","lemma":"σοῦ","morph":"RP.GS"},{"w":"καὶ","lemma":"καί","morph":"C"},{"w":"εἰς","lemma":"εἰς","morph":"P"},{"w":"τὴν","lemma":"ὁ","morph":"RA.ASF"},{"w":"ζωὴν","lemma":"ζωή","morph":"N.ASF"},{"w":"σῶν","lemma":"σός","morph":"A.GPM"},{"w":"θεραπόντων","lemma":"θεράπων","morph":"N.GPM"}],"20a":[{"w":"βδέλυγμα","lemma":"βδέλυγμα","morph":"N.NSN"},{"w":"κυρίῳ","lemma":"κύριος","morph":"N.DSM"},{"w":"στηρίζων","lemma":"στηρίζω","morph":"V.PAPNSM"},{"w":"ὀφθαλμόν","lemma":"ὀφθαλμός","morph":"N.ASM"},{"w":"καὶ","lemma":"καί","morph":"C"},{"w":"οἱ","lemma":"ὁ","morph":"RA.NPM"},{"w":"ἀπαίδευτοι","lemma":"ἀπαίδευτος","morph":"A.NPM"},{"w":"ἀκρατεῖς","lemma":"ἀκρατής","morph":"A.NPM"},{"w":"γλώσσῃ","lemma":"γλῶσσα","morph":"N.DSF"}],"21a":[{"w":"καρδία","lemma":"καρδία","morph":"N.NSF"},{"w":"ἀνόμου","lemma":"ἄνομος","morph":"A.GSM"},{"w":"ἐκζητεῖ","lemma":"ἐκζητέω","morph":"V.PAI3S"},{"w":"κακά","lemma":"κακός","morph":"A.APN"},{"w":"καρδία","lemma":"καρδία","morph":"N.NSF"},{"w":"δὲ","lemma":"δέ","morph":"X"},{"w":"εὐθὴς","lemma":"εὐθής","morph":"A.NSF"},{"w":"ἐκζητεῖ","lemma":"ἐκζητέω","morph":"V.PAI3S"},{"w":"γνῶσιν","lemma":"γνῶσις","morph":"N.ASF"}]}}