{"1":{"raw":"<Q><l>הוֹדוּ</l><n>1</n> <s>H3034</s> <m>VhAIPM2</m> <E>Alabad<e><q> <Q><l>לַ</l><n>2</n> <m>PL</m> <E>a<e><q> <Q><l>יהוה</l><n>3</n> <s>H3068</s> <m>NPDSMN</m> <E>Jehová,<e><q> <Q><l>קִרְאוּ</l><n>4</n> <s>H7121</s> <m>VqAIPM2</m> <E>invocad<e><q> <Q><l>בִּ</l><n>5</n> <m>PB</m> <z>s/t</z><q> <Q><l>ֹו</l><n>7</n> <m>RBSM3</m> <E>su<e><q> <Q><l>שְׁמ</l><n>6</n> <s>H8034</s> <m>NCcSMS</m> <E>nombre;<e> <x><f>→</f>Dad</x> <x><f>→</f>a</x><q> <Q><l>הוֹדִיעוּ</l><n>8</n> <s>H3045</s> <m>VhAIPM2</m> <E>conocer<e><q> <Q><l>ו</l><n>13</n> <m>RBSM3</m> <E>sus<e><q> <Q><l>עֲלִילוֹתָי</l><n>12</n> <s>H5949</s> <m>NCcPFS</m> <E>obras<e><q> <Q><l>ב</l><n>9</n> <m>PB</m> <E>en<e><q> <Q><l>ָ</l><n>10</n> <m>XD</m> <E>los<e><q> <Q><l>עַמִּים</l><n>11</n> <s>H5971</s> <m>NCcPMNh</m> <E>pueblos.<e><q>","tokens":[{"orig":"הוֹדוּ","strongs":"H3034","morphs":"VhAIPM2","es":"Alabad","num":"1"},{"orig":"לַ","morphs":"PL","es":"a","num":"2"},{"orig":"יהוה","strongs":"H3068","morphs":"NPDSMN","es":"Jehová,","num":"3"},{"orig":"קִרְאוּ","strongs":"H7121","morphs":"VqAIPM2","es":"invocad","num":"4"},{"orig":"בִּ","morphs":"PB","num":"5","notrans":"s/t"},{"orig":"ֹו","morphs":"RBSM3","es":"su","num":"7"},{"orig":"שְׁמ","strongs":"H8034","morphs":"NCcSMS","es":"nombre;","num":"6","added":["→Dad","→a"],"marks":["→","→"]},{"orig":"הוֹדִיעוּ","strongs":"H3045","morphs":"VhAIPM2","es":"conocer","num":"8"},{"orig":"ו","morphs":"RBSM3","es":"sus","num":"13"},{"orig":"עֲלִילוֹתָי","strongs":"H5949","morphs":"NCcPFS","es":"obras","num":"12"},{"orig":"ב","morphs":"PB","es":"en","num":"9"},{"orig":"ָ","morphs":"XD","num":"10","notrans":"s/t"},{"orig":"עַמִּים","strongs":"H5971","morphs":"NCcPMNh","es":"pueblos.","num":"11"}]},"2":{"raw":" <f>‹</f><q><Q><l>שִׁירוּ־</l><n>1</n> <l>ל</l><n>2</n> <l>ֹו</l><n>3</n> <f>›</f><s>H7891</s> <m>VqAIPM2</m><m>,</m> <m>PL</m><m>,</m> <m>RBSM3</m> <E>Cantadle,<e> <x><f>→</f>cantadle</x> <f>‹</f><q><Q><l>זַמְּרוּ־</l><n>4</n> <l>ל</l><n>5</n> <l>ֹו</l><n>6</n> <f>›</f><s>H2167</s> <m>VpAIPM2</m><m>,</m> <m>PL</m><m>,</m> <m>RBSM3</m> <E>salmos;<e><q> <Q><l>שִׂיחוּ</l><n>7</n> <s>H7878</s> <m>VqAIPM2</m> <E>Hablad<e><q> <Q><l>בְּ</l><n>8</n> <m>PB</m> <E>de<e><q> <Q><l>כָל־</l><n>9</n> <s>H3605</s> <m>NCACCC</m> <E>todas<e><q> <Q><l>ו</l><n>11</n> <m>RBSM3</m> <E>sus<e><q> <Q><l>נִפְלְאוֹתָי</l><n>10</n> <s>H6381</s> <m>NCcPFS</m> <E>maravillas.<e><q>","tokens":[{"orig":["שִׁירוּ־","ל","ֹו"],"strongs":"H7891","morphs":["VqAIPM2",",","PL",",","RBSM3"],"es":"Cantadle,","num":["1","2","3"],"added":"→cantadle","marks":["›","→","‹"]},{"orig":["זַמְּרוּ־","ל","ֹו"],"strongs":"H2167","morphs":["VpAIPM2",",","PL",",","RBSM3"],"es":"salmos;","num":["4","5","6"],"marks":"›"},{"orig":"שִׂיחוּ","strongs":"H7878","morphs":"VqAIPM2","es":"Hablad","num":"7"},{"orig":"בְּ","morphs":"PB","es":"de","num":"8"},{"orig":"כָל־","strongs":"H3605","morphs":"NCACCC","es":"todas","num":"9"},{"orig":"ו","morphs":"RBSM3","es":"sus","num":"11"},{"orig":"נִפְלְאוֹתָי","strongs":"H6381","morphs":"NCcPFS","es":"maravillas.","num":"10"}]},"3":{"raw":"<Q><l>הִתְהַלְלוּ</l><n>1</n> <s>H1984</s> <m>VtMIPM2</m> <E>Gloriaos<e><q> <Q><l>בְּ</l><n>2</n> <m>PB</m> <E>en<e><q> <Q><l>ֹו</l><n>5</n> <m>RBSM3</m> <E>su<e><q> <Q><l>קָדְשׁ</l><n>4</n> <s>H6944</s> <m>NCcSMS</m> <E>santo<e><q> <Q><l>שֵׁם</l><n>3</n> <s>H8034</s> <m>NCcSMC</m> <E>nombre;<e><q> <Q><l>יִשְׂמַח</l><n>6</n> <s>H8055</s> <m>VqAJSM3</m> <E>Alégrese<e> <x><f>→</f>el</x><q> <Q><l>לֵב</l><n>7</n> <s>H3820</s> <m>NCcSMN</m> <E>corazón<e> <x><f> ← </f>de</x> <x><f>→</f>los</x> <x><f>→</f>que</x><q> <Q><l>מְבַקְשֵׁי</l><n>8</n> <s>H1245</s> <m>VpAtPM-C</m> <E>buscan<e> <x><f> ← </f>a</x><q> <Q><l>יהוה</l><n>9</n> <s>H3068</s> <m>NPDSMN</m> <E>Jehová.<e><q>","tokens":[{"orig":"הִתְהַלְלוּ","strongs":"H1984","morphs":"VtMIPM2","es":"Gloriaos","num":"1"},{"orig":"בְּ","morphs":"PB","es":"en","num":"2"},{"orig":"ֹו","morphs":"RBSM3","es":"su","num":"5"},{"orig":"קָדְשׁ","strongs":"H6944","morphs":"NCcSMS","es":"santo","num":"4"},{"orig":"שֵׁם","strongs":"H8034","morphs":"NCcSMC","es":"nombre;","num":"3"},{"orig":"יִשְׂמַח","strongs":"H8055","morphs":"VqAJSM3","es":"Alégrese","num":"6","added":"→el","marks":"→"},{"orig":"לֵב","strongs":"H3820","morphs":"NCcSMN","es":"corazón","num":"7","added":["← de","→los","→que"],"marks":["←","→","→"]},{"orig":"מְבַקְשֵׁי","strongs":"H1245","morphs":"VpAtPM-C","es":"buscan","num":"8","added":"← a","marks":"←"},{"orig":"יהוה","strongs":"H3068","morphs":"NPDSMN","es":"Jehová.","num":"9"}]},"4":{"raw":"<Q><l>דִּרְשׁוּ</l><n>1</n> <s>H1875</s> <m>VqAIPM2</m> <E>Buscad<e> <E>a<e><q> <Q><l>יהוה</l><n>2</n> <s>H3068</s> <m>NPDSMN</m> <E>Jehová<e><q> <Q><l>וְ</l><n>3</n> <m>CC</m> <E>y<e><q> <Q><l>ֹו</l><n>5</n> <m>RBSM3</m> <E>su<e><q> <Q><l>עֻזּ</l><n>4</n> <s>H5797</s> <m>NCcSMS</m> <E>poder;<e><q> <Q><l>בַּקְּשׁוּ</l><n>6</n> <s>H1245</s> <m>VpAIPM2</m> <E>Buscad<e><q> <Q><l>תָּמִיד</l><n>9</n> <s>H8548</s> <m>NCcSMN</m> <E>siempre<e><q> <Q><l>ו</l><n>8</n> <m>RBSM3</m> <E>su<e><q> <Q><l>פָנָי</l><n>7</n> <s>H6440</s> <m>NCcPMS</m> <E>rostro.<e><q>","tokens":[{"orig":"דִּרְשׁוּ","strongs":"H1875","morphs":"VqAIPM2","es":["Buscad","a"],"num":"1"},{"orig":"יהוה","strongs":"H3068","morphs":"NPDSMN","es":"Jehová","num":"2"},{"orig":"וְ","morphs":"CC","es":"y","num":"3"},{"orig":"ֹו","morphs":"RBSM3","es":"su","num":"5"},{"orig":"עֻזּ","strongs":"H5797","morphs":"NCcSMS","es":"poder;","num":"4"},{"orig":"בַּקְּשׁוּ","strongs":"H1245","morphs":"VpAIPM2","es":"Buscad","num":"6"},{"orig":"תָּמִיד","strongs":"H8548","morphs":"NCcSMN","es":"siempre","num":"9"},{"orig":"ו","morphs":"RBSM3","es":"su","num":"8"},{"orig":"פָנָי","strongs":"H6440","morphs":"NCcPMS","es":"rostro.","num":"7"}]},"5":{"raw":"<Q><l>זִכְרוּ</l><n>1</n> <s>H2142</s> <m>VqAIPM2</m> <E>Acordaos<e> <E>de<e> <E>las<e><q> <Q><l>נִפְלְאוֹתָי</l><n>2</n> <s>H6381</s> <m>NCcPFS</m> <E>maravillas<e><q> <Q><l>ו</l><n>3</n> <m>RBSM3</m> <z>s/t</z><q> <Q><l>אֲשֶׁר־</l><n>4</n> <s>H834</s> <m>XN</m> <E>que<e> <x><f>→</f>él</x> <x><f>→</f>ha</x><q> <Q><l>עָשָׂה</l><n>5</n> <s>H6213</s> <m>VqAsSM3</m> <E>hecho,<e> <E>De<e><q> <Q><l>ו</l><n>7</n> <m>RBSM3</m> <E>sus<e><q> <Q><l>מֹפְתָי</l><n>6</n> <s>H4159</s> <m>NCcPMS</m> <E>prodigios<e><q> <Q><l>וּ</l><n>8</n> <m>CC</m> <E>y<e> <E>de<e> <x><f>→</f>los</x><q> <Q><l>מִשְׁפְּטֵי־</l><n>9</n> <s>H4941</s> <m>NCcPMC</m> <E>juicios<e> <x><f> ← </f>de</x><q> <Q><l>ו</l><n>11</n> <m>RBSM3</m> <E>su<e><q> <Q><l>פִי</l><n>10</n> <s>H6310</s> <m>NCcSMS</m> <E>boca,<e><q>","tokens":[{"orig":"זִכְרוּ","strongs":"H2142","morphs":"VqAIPM2","es":["Acordaos","de","las"],"num":"1"},{"orig":"נִפְלְאוֹתָי","strongs":"H6381","morphs":"NCcPFS","es":"maravillas","num":"2"},{"orig":"ו","morphs":"RBSM3","num":"3","notrans":"s/t"},{"orig":"אֲשֶׁר־","strongs":"H834","morphs":"XN","es":"que","num":"4","added":["→él","→ha"],"marks":["→","→"]},{"orig":"עָשָׂה","strongs":"H6213","morphs":"VqAsSM3","es":["hecho,","De"],"num":"5"},{"orig":"ו","morphs":"RBSM3","es":"sus","num":"7"},{"orig":"מֹפְתָי","strongs":"H4159","morphs":"NCcPMS","es":"prodigios","num":"6"},{"orig":"וּ","morphs":"CC","es":["y","de"],"num":"8","added":"→los","marks":"→"},{"orig":"מִשְׁפְּטֵי־","strongs":"H4941","morphs":"NCcPMC","es":"juicios","num":"9","added":"← de","marks":"←"},{"orig":"ו","morphs":"RBSM3","es":"su","num":"11"},{"orig":"פִי","strongs":"H6310","morphs":"NCcSMS","es":"boca,","num":"10"}]},"6":{"raw":"<E>Oh<e> <E>vosotros,<e><q> <Q><l>זֶרַע</l><n>1</n> <s>H2233</s> <m>NCcSMC</m> <E>descendencia<e> <x><f> ← </f>de</x><q> <Q><l>אַבְרָהָם</l><n>2</n> <s>H85</s> <m>NPHSMN</m> <E>Abraham<e><q> <Q><l>ֹו</l><n>4</n> <m>RBSM3</m> <E>su<e><q> <Q><l>עַבְדּ</l><n>3</n> <s>H5650</s> <m>NCcSMS</m> <E>siervo,<e><q> <Q><l>בְּנֵי</l><n>5</n> <s>H1121</s> <m>NCcPMC</m> <E>Hijos<e> <x><f> ← </f>de</x><q> <Q><l>יַעֲקֹב</l><n>6</n> <s>H3290</s> <m>NPHSMN</m> <E>Jacob,<e><q> <Q><l>ו</l><n>8</n> <m>RBSM3</m> <E>sus<e><q> <Q><l>בְּחִירָי</l><n>7</n> <s>H972</s> <m>NCcPMS</m> <E>escogidos.<e><q>","tokens":[{"orig":"זֶרַע","strongs":"H2233","morphs":"NCcSMC","es":"descendencia","num":"1","added":"← de","marks":"←"},{"orig":"אַבְרָהָם","strongs":"H85","morphs":"NPHSMN","es":"Abraham","num":"2"},{"orig":"ֹו","morphs":"RBSM3","es":"su","num":"4"},{"orig":"עַבְדּ","strongs":"H5650","morphs":"NCcSMS","es":"siervo,","num":"3"},{"orig":"בְּנֵי","strongs":"H1121","morphs":"NCcPMC","es":"Hijos","num":"5","added":"← de","marks":"←"},{"orig":"יַעֲקֹב","strongs":"H3290","morphs":"NPHSMN","es":"Jacob,","num":"6"},{"orig":"ו","morphs":"RBSM3","es":"sus","num":"8"},{"orig":"בְּחִירָי","strongs":"H972","morphs":"NCcPMS","es":"escogidos.","num":"7"}]},"7":{"raw":"<Q><l>הוּא</l><n>1</n> <s>H1931</s> <m>RFSM3</m> <E>El<e> <E>es<e><q> <Q><l>יהוה</l><n>2</n> <s>H3068</s> <m>NPDSMN</m> <E>Jehová<e><q> <Q><l>נוּ</l><n>4</n> <m>RBPC1</m> <E>nuestro<e><q> <Q><l>אֱלֹהֵי</l><n>3</n> <s>H430</s> <m>NCcPMS</m> <E>Dios;<e><q> <Q><l>בְּ</l><n>5</n> <m>PB</m> <E>En<e><q> <Q><l>כָל־</l><n>6</n> <s>H3605</s> <m>NCACCC</m> <E>toda<e><q> <Q><l>הָ</l><n>7</n> <m>XD</m> <E>la<e><q> <Q><l>אָרֶץ</l><n>8</n> <s>H776</s> <m>NCcSFPH</m> <E>tierra<e> <E>están<e><q> <Q><l>ו</l><n>10</n> <m>RBSM3</m> <E>sus<e><q> <Q><l>מִשְׁפָּטָי</l><n>9</n> <s>H4941</s> <m>NCcPMS</m> <E>juicios.<e><q>","tokens":[{"orig":"הוּא","strongs":"H1931","morphs":"RFSM3","es":["El","es"],"num":"1"},{"orig":"יהוה","strongs":"H3068","morphs":"NPDSMN","es":"Jehová","num":"2"},{"orig":"נוּ","morphs":"RBPC1","es":"nuestro","num":"4"},{"orig":"אֱלֹהֵי","strongs":"H430","morphs":"NCcPMS","es":"Dios;","num":"3"},{"orig":"בְּ","morphs":"PB","es":"En","num":"5"},{"orig":"כָל־","strongs":"H3605","morphs":"NCACCC","es":"toda","num":"6"},{"orig":"הָ","morphs":"XD","es":"la","num":"7"},{"orig":"אָרֶץ","strongs":"H776","morphs":"NCcSFPH","es":["tierra","están"],"num":"8"},{"orig":"ו","morphs":"RBSM3","es":"sus","num":"10"},{"orig":"מִשְׁפָּטָי","strongs":"H4941","morphs":"NCcPMS","es":"juicios.","num":"9"}]},"8":{"raw":" <x><f>→</f>Se</x><q> <Q><l>זָכַר</l><n>1</n> <s>H2142</s> <m>VqAsSM3</m> <E>acordó<e><q> <Q><l>לְ</l><n>2</n> <m>PL</m> <E>para<e><q> <Q><l>עוֹלָם</l><n>3</n> <s>H5769</s> <m>NCcSMN</m> <E>siempre<e> <E>de<e><q> <Q><l>ֹו</l><n>5</n> <m>RBSM3</m> <E>su<e><q> <Q><l>בְּרִית</l><n>4</n> <s>H1285</s> <m>NCcSFS</m> <E>pacto;<e> <E>De<e> <E>la<e><q> <Q><l>דָּבָר</l><n>6</n> <s>H1697</s> <m>NCcSMN</m> <E>palabra<e> <E>que<e><q> <Q><l>צִוָּה</l><n>7</n> <s>H6680</s> <m>VpAsSM3</m> <E>mandó<e><q> <Q><l>לְ</l><n>8</n> <m>PL</m> <E>para<e><q> <Q><l>אֶלֶף</l><n>9</n> <s>H505</s> <m>NCNSMN</m> <E>mil<e><q> <Q><l>דּוֹר</l><n>10</n> <s>H1755</s> <m>NCcSMN</m> <E>generaciones,<e><q>","tokens":[{"orig":"זָכַר","strongs":"H2142","morphs":"VqAsSM3","es":"acordó","num":"1"},{"orig":"לְ","morphs":"PL","es":"para","num":"2"},{"orig":"עוֹלָם","strongs":"H5769","morphs":"NCcSMN","es":["siempre","de"],"num":"3"},{"orig":"ֹו","morphs":"RBSM3","es":"su","num":"5"},{"orig":"בְּרִית","strongs":"H1285","morphs":"NCcSFS","es":["pacto;","De","la"],"num":"4"},{"orig":"דָּבָר","strongs":"H1697","morphs":"NCcSMN","es":["palabra","que"],"num":"6"},{"orig":"צִוָּה","strongs":"H6680","morphs":"VpAsSM3","es":"mandó","num":"7"},{"orig":"לְ","morphs":"PL","es":"para","num":"8"},{"orig":"אֶלֶף","strongs":"H505","morphs":"NCNSMN","es":"mil","num":"9"},{"orig":"דּוֹר","strongs":"H1755","morphs":"NCcSMN","es":"generaciones,","num":"10"}]},"9":{"raw":" <x><f>→</f>La</x><q> <Q><l>אֲשֶׁר</l><n>1</n> <s>H834</s> <m>XN</m> <E>cual<e><q> <Q><l>כָּרַת</l><n>2</n> <s>H3772</s> <m>VqAsSM3</m> <E>concertó<e><q> <Q><l>אֶת־</l><n>3</n> <s>H854</s> <m>PW</m> <E>con<e><q> <Q><l>אַבְרָהָם</l><n>4</n> <s>H85</s> <m>NPHSMN</m> <E>Abraham,<e><q> <Q><l>וּ</l><n>5</n> <m>CC</m> <E>Y<e> <E>de<e><q> <Q><l>ֹו</l><n>7</n> <m>RBSM3</m> <E>su<e><q> <Q><l>שְׁבוּעָת</l><n>6</n> <s>H7621</s> <m>NCcSFS</m> <E>juramento<e><q> <Q><l>לְ</l><n>8</n> <m>PL</m> <E>a<e><q> <Q><l>יִשְׂחָק</l><n>9</n> <s>H3446</s> <m>NPHSMN</m> <E>Isaac.<e><q>","tokens":[{"orig":"אֲשֶׁר","strongs":"H834","morphs":"XN","es":"cual","num":"1"},{"orig":"כָּרַת","strongs":"H3772","morphs":"VqAsSM3","es":"concertó","num":"2"},{"orig":"אֶת־","strongs":"H854","morphs":"PW","es":"con","num":"3"},{"orig":"אַבְרָהָם","strongs":"H85","morphs":"NPHSMN","es":"Abraham,","num":"4"},{"orig":"וּ","morphs":"CC","es":["Y","de"],"num":"5"},{"orig":"ֹו","morphs":"RBSM3","es":"su","num":"7"},{"orig":"שְׁבוּעָת","strongs":"H7621","morphs":"NCcSFS","es":"juramento","num":"6"},{"orig":"לְ","morphs":"PL","es":"a","num":"8"},{"orig":"יִשְׂחָק","strongs":"H3446","morphs":"NPHSMN","es":"Isaac.","num":"9"}]},"10":{"raw":"<Q><l>וַ</l><n>1</n> <m>Cc</m> <z>s/t</z><q> <Q><l>ֶהָ</l><n>3</n> <m>RBSF3</m> <E>La<e><q> <Q><l>יַּעֲמִיד</l><n>2</n> <s>H5975</s> <m>VhAmSM3</m> <E>estableció<e><q> <Q><l>לְ</l><n>4</n> <m>PL</m> <E>a<e><q> <Q><l>יַעֲקֹב</l><n>5</n> <s>H3290</s> <m>NPHSMN</m> <E>Jacob<e><q> <Q><l>לְ</l><n>6</n> <m>PL</m> <E>por<e><q> <Q><l>חֹק</l><n>7</n> <s>H2706</s> <m>NCcSMN</m> <E>decreto,<e><q> <Q><l>לְ</l><n>8</n> <m>PL</m> <E>A<e><q> <Q><l>יִשְׂרָאֵל</l><n>9</n> <s>H3478</s> <m>NPHSMN</m> <E>Israel<e> <E>por<e><q> <Q><l>בְּרִית</l><n>10</n> <s>H1285</s> <m>NCcSFC</m> <E>pacto<e><q> <Q><l>עוֹלָם</l><n>11</n> <s>H5769</s> <m>NCcSMN</m> <E>sempiterno,<e><q>","tokens":[{"orig":"וַ","morphs":"Cc","num":"1","notrans":"s/t"},{"orig":"ֶהָ","morphs":"RBSF3","es":"La","num":"3"},{"orig":"יַּעֲמִיד","strongs":"H5975","morphs":"VhAmSM3","es":"estableció","num":"2"},{"orig":"לְ","morphs":"PL","es":"a","num":"4"},{"orig":"יַעֲקֹב","strongs":"H3290","morphs":"NPHSMN","es":"Jacob","num":"5"},{"orig":"לְ","morphs":"PL","es":"por","num":"6"},{"orig":"חֹק","strongs":"H2706","morphs":"NCcSMN","es":"decreto,","num":"7"},{"orig":"לְ","morphs":"PL","es":"A","num":"8"},{"orig":"יִשְׂרָאֵל","strongs":"H3478","morphs":"NPHSMN","es":["Israel","por"],"num":"9"},{"orig":"בְּרִית","strongs":"H1285","morphs":"NCcSFC","es":"pacto","num":"10"},{"orig":"עוֹלָם","strongs":"H5769","morphs":"NCcSMN","es":"sempiterno,","num":"11"}]},"11":{"raw":" <f>‹</f><q><Q><l>לֵ</l><n>1</n> <l>אמֹר</l><n>2</n> <f>›</f><s>H559</s> <m>PL</m><m>,</m> <m>VqAT---C</m> <E>Diciendo:<e><q> <Q><l>לְ</l><n>3</n> <m>PL</m> <E>A<e><q> <Q><l>ךָ</l><n>4</n> <m>RBSM2</m> <E>ti<e> <E>te<e><q> <Q><l>אֶתֵּן</l><n>5</n> <s>H5414</s> <m>VqAMSC1</m> <E>daré<e><q> <Q><l>אֶת־</l><n>6</n> <s>H853</s> <m>PA</m> <z>s/t</z> <x><f>→</f>la</x><q> <Q><l>אֶרֶץ־</l><n>7</n> <s>H776</s> <m>NCcSFC</m> <E>tierra<e> <x><f> ← </f>de</x><q> <Q><l>כְּנָעַן</l><n>8</n> <s>H3667</s> <m>NPLSFP</m> <E>Canaán<e> <E>Como<e><q> <Q><l>חֶבֶל</l><n>9</n> <s>H2256</s> <m>NCcSMC</m> <E>porción<e> <x><f> ← </f>de</x><q> <Q><l>ְכֶם</l><n>11</n> <m>RBPM2</m> <E>vuestra<e><q> <Q><l>נַחֲלַת</l><n>10</n> <s>H5159</s> <m>NCcSFS</m> <E>heredad.<e><q>","tokens":[{"orig":["לֵ","אמֹר"],"strongs":"H559","morphs":["PL",",","VqAT---C"],"es":"Diciendo:","num":["1","2"],"marks":"›"},{"orig":"לְ","morphs":"PL","es":"A","num":"3"},{"orig":"ךָ","morphs":"RBSM2","es":["ti","te"],"num":"4"},{"orig":"אֶתֵּן","strongs":"H5414","morphs":"VqAMSC1","es":"daré","num":"5"},{"orig":"אֶת־","strongs":"H853","morphs":"PA","num":"6","added":"→la","notrans":"s/t","marks":"→"},{"orig":"אֶרֶץ־","strongs":"H776","morphs":"NCcSFC","es":"tierra","num":"7","added":"← de","marks":"←"},{"orig":"כְּנָעַן","strongs":"H3667","morphs":"NPLSFP","es":["Canaán","Como"],"num":"8"},{"orig":"חֶבֶל","strongs":"H2256","morphs":"NCcSMC","es":"porción","num":"9","added":"← de","marks":"←"},{"orig":"ְכֶם","morphs":"RBPM2","es":"vuestra","num":"11"},{"orig":"נַחֲלַת","strongs":"H5159","morphs":"NCcSFS","es":"heredad.","num":"10"}]},"12":{"raw":"<Q><l>בִּ</l><n>1</n> <m>PB</m> <E>Cuando<e><q> <Q><l>ָם</l><n>3</n> <m>RBPM3</m> <E>ellos<e><q> <Q><l>הְיוֹת</l><n>2</n> <s>H1961</s> <m>VqAT---S</m> <E>eran<e><q> <Q><l>מְתֵי</l><n>4</n> <s>H4962</s> <m>NCcPMC</m> <E>pocos<e> <E>en<e><q> <Q><l>מִסְפָּר</l><n>5</n> <s>H4557</s> <m>NCcSMN</m> <E>número,<e><q> <Q><l>כִּ</l><n>6</n> <m>PK</m> <z>s/t</z><q> <Q><l>מְעַט</l><n>7</n> <s>H4592</s> <m>NCcSMN</m> <z>s/t</z><q> <Q><l>וְ</l><n>8</n> <m>CC</m> <E>Y<e><q> <Q><l>גָרִים</l><n>9</n> <s>H1481</s> <m>VqApPM-N</m> <E>forasteros<e><q> <Q><l>בּ</l><n>10</n> <m>PB</m> <E>en<e><q> <Q><l>ָהּ</l><n>11</n> <m>RBSF3</m> <E>ella,<e><q>","tokens":[{"orig":"בִּ","morphs":"PB","es":"Cuando","num":"1"},{"orig":"ָם","morphs":"RBPM3","es":"ellos","num":"3"},{"orig":"הְיוֹת","strongs":"H1961","morphs":"VqAT---S","es":"eran","num":"2"},{"orig":"מְתֵי","strongs":"H4962","morphs":"NCcPMC","es":["pocos","en"],"num":"4"},{"orig":"מִסְפָּר","strongs":"H4557","morphs":"NCcSMN","es":"número,","num":"5"},{"orig":"כִּ","morphs":"PK","num":"6","notrans":"s/t"},{"orig":"מְעַט","strongs":"H4592","morphs":"NCcSMN","num":"7","notrans":"s/t"},{"orig":"וְ","morphs":"CC","es":"Y","num":"8"},{"orig":"גָרִים","strongs":"H1481","morphs":"VqApPM-N","es":"forasteros","num":"9"},{"orig":"בּ","morphs":"PB","es":"en","num":"10"},{"orig":"ָהּ","morphs":"RBSF3","es":"ella,","num":"11"}]},"13":{"raw":"<Q><l>וַ</l><n>1</n> <m>Cc</m> <E>Y<e><q> <Q><l>יִּתְהַלְּכוּ</l><n>2</n> <s>H1980</s> <m>VtMmPM3</m> <E>andaban<e><q> <Q><l>מִ</l><n>3</n> <m>PM</m> <E>de<e><q> <Q><l>גּוֹי</l><n>4</n> <s>H1471</s> <m>NCcSMN</m> <E>nación<e><q> <Q><l>אֶל־</l><n>5</n> <s>H413</s> <m>PU</m> <E>en<e><q> <Q><l>גּוֹי</l><n>6</n> <s>H1471</s> <m>NCcSMN</m> <E>nación,<e><q> <Q><l>מִ</l><n>7</n> <m>PM</m> <E>De<e> <E>un<e><q> <Q><l>מַּמְלָכָה</l><n>8</n> <s>H4467</s> <m>NCcSFN</m> <E>reino<e><q> <Q><l>אֶל־</l><n>9</n> <s>H413</s> <m>PU</m> <E>a<e><q> <Q><l>אַחֵר</l><n>11</n> <s>H312</s> <m>NCJSMN</m> <E>otro<e><q> <Q><l>עַם</l><n>10</n> <s>H5971</s> <m>NCcSMC</m> <E>pueblo,<e><q>","tokens":[{"orig":"וַ","morphs":"Cc","es":"Y","num":"1"},{"orig":"יִּתְהַלְּכוּ","strongs":"H1980","morphs":"VtMmPM3","es":"andaban","num":"2"},{"orig":"מִ","morphs":"PM","es":"de","num":"3"},{"orig":"גּוֹי","strongs":"H1471","morphs":"NCcSMN","es":"nación","num":"4"},{"orig":"אֶל־","strongs":"H413","morphs":"PU","es":"en","num":"5"},{"orig":"גּוֹי","strongs":"H1471","morphs":"NCcSMN","es":"nación,","num":"6"},{"orig":"מִ","morphs":"PM","es":["De","un"],"num":"7"},{"orig":"מַּמְלָכָה","strongs":"H4467","morphs":"NCcSFN","es":"reino","num":"8"},{"orig":"אֶל־","strongs":"H413","morphs":"PU","es":"a","num":"9"},{"orig":"אַחֵר","strongs":"H312","morphs":"NCJSMN","es":"otro","num":"11"},{"orig":"עַם","strongs":"H5971","morphs":"NCcSMC","es":"pueblo,","num":"10"}]},"14":{"raw":"<Q><l>לֹא־</l><n>1</n> <s>H3808</s> <m>ANN</m> <E>No<e><q> <Q><l>הִנִּיחַ</l><n>2</n> <s>H3240</s> <m>VhAsSM3</m> <E>consintió<e> <E>que<e><q> <Q><l>אָדָם</l><n>3</n> <s>H120</s> <m>NCcSMN</m> <E>«nadie » *<e><q> <Q><l>ָם</l><n>6</n> <m>RBPM3</m> <E>los<e> <f>‹</f><q><Q><l>לְ</l><n>4</n> <l>עָשְׁק</l><n>5</n> <f>›</f><s>H6231</s> <m>PL</m><m>,</m> <m>VqAT---S</m> <E>agraviase,<e><q> <Q><l>וַ</l><n>7</n> <m>Cc</m> <E>Y<e> <E>por<e> <E>causa<e><q> <Q><l>עֲלֵי</l><n>9</n> <s>H5921</s> <m>Pu</m> <E>de<e><q> <Q><l>הֶם</l><n>10</n> <m>RBPM3</m> <E>ellos<e><q> <Q><l>יּוֹכַח</l><n>8</n> <s>H3198</s> <m>VhAmSM3</m> <E>castigó<e> <E>a<e> <E>los<e><q> <Q><l>מְלָכִים</l><n>11</n> <s>H4428</s> <m>NCcPMN</m> <E>reyes.<e><q>","tokens":[{"orig":"לֹא־","strongs":"H3808","morphs":"ANN","es":"No","num":"1"},{"orig":"הִנִּיחַ","strongs":"H3240","morphs":"VhAsSM3","es":["consintió","que"],"num":"2"},{"orig":"אָדָם","strongs":"H120","morphs":"NCcSMN","es":"«nadie » *","num":"3"},{"orig":"ָם","morphs":"RBPM3","es":"los","num":"6","marks":"‹"},{"orig":["לְ","עָשְׁק"],"strongs":"H6231","morphs":["PL",",","VqAT---S"],"es":"agraviase,","num":["4","5"],"marks":"›"},{"orig":"וַ","morphs":"Cc","es":["Y","por","causa"],"num":"7"},{"orig":"עֲלֵי","strongs":"H5921","morphs":"Pu","es":"de","num":"9"},{"orig":"הֶם","morphs":"RBPM3","es":"ellos","num":"10"},{"orig":"יּוֹכַח","strongs":"H3198","morphs":"VhAmSM3","es":["castigó","a","los"],"num":"8"},{"orig":"מְלָכִים","strongs":"H4428","morphs":"NCcPMN","es":"reyes.","num":"11"}]},"15":{"raw":"<Q><l>אַל־</l><n>1</n> <s>H408</s> <m>AND</m> <E>No<e><q> <Q><l>תִּגְּעוּ</l><n>2</n> <s>H5060</s> <m>VqAJPM2</m> <E>toquéis,<e> <E>dijo,<e><q> <Q><l>בִ</l><n>3</n> <m>PB</m> <E>a<e><q> <Q><l>י</l><n>5</n> <m>RBSC1</m> <E>mis<e><q> <Q><l>מְשִׁיחָ</l><n>4</n> <s>H4899</s> <m>NCcPMS</m> <E>ungidos,<e><q> <Q><l>וְ</l><n>6</n> <m>CC</m> <z>s/t</z><q> <Q><l>אַל־</l><n>10</n> <s>H408</s> <m>AND</m> <E>Ni<e> <x><f>→</f>hagáis</x><q> <Q><l>תָּרֵעוּ</l><n>11</n> <s>H7489</s> <m>VhAJPM2</m> <E>mal<e><q> <Q><l>לִ</l><n>7</n> <m>PL</m> <E>a<e><q> <Q><l>י</l><n>9</n> <m>RBSC1</m> <E>mis<e><q> <Q><l>נְבִיאַ</l><n>8</n> <s>H5030</s> <m>NCcPMS</m> <E>profetas.<e><q>","tokens":[{"orig":"אַל־","strongs":"H408","morphs":"AND","es":"No","num":"1"},{"orig":"תִּגְּעוּ","strongs":"H5060","morphs":"VqAJPM2","es":["toquéis,","dijo,"],"num":"2"},{"orig":"בִ","morphs":"PB","es":"a","num":"3"},{"orig":"י","morphs":"RBSC1","es":"mis","num":"5"},{"orig":"מְשִׁיחָ","strongs":"H4899","morphs":"NCcPMS","es":"ungidos,","num":"4"},{"orig":"וְ","morphs":"CC","num":"6","notrans":"s/t"},{"orig":"אַל־","strongs":"H408","morphs":"AND","es":"Ni","num":"10","added":"→hagáis","marks":"→"},{"orig":"תָּרֵעוּ","strongs":"H7489","morphs":"VhAJPM2","es":"mal","num":"11"},{"orig":"לִ","morphs":"PL","es":"a","num":"7"},{"orig":"י","morphs":"RBSC1","es":"mis","num":"9"},{"orig":"נְבִיאַ","strongs":"H5030","morphs":"NCcPMS","es":"profetas.","num":"8"}]},"16":{"raw":"<Q><l>וַ</l><n>1</n> <m>Cc</m> <z>s/t</z><q> <Q><l>יִּקְרָא</l><n>2</n> <s>H7121</s> <m>VqAmSM3</m> <E>Trajo<e><q> <Q><l>רָעָב</l><n>3</n> <s>H7458</s> <m>NCcSMN</m> <E>hambre<e><q> <Q><l>עַל־</l><n>4</n> <s>H5921</s> <m>Pu</m> <E>sobre<e><q> <Q><l>הָ</l><n>5</n> <m>XD</m> <E>la<e><q> <Q><l>אָרֶץ</l><n>6</n> <s>H776</s> <m>NCcSFPH</m> <E>tierra,<e> <E>Y<e><q> <Q><l>שָׁבָר</l><n>10</n> <s>H7665</s> <m>VqAsSM3</m> <E>quebrantó<e><q> <Q><l>כָּל־</l><n>7</n> <s>H3605</s> <m>NCACCC</m> <E>todo<e><q> <Q><l>מַטֵּה־</l><n>8</n> <s>H4294</s> <m>NCcSMC</m> <E>sustento<e> <x><f> ← </f>de</x><q> <Q><l>לֶחֶם</l><n>9</n> <s>H3899</s> <m>NCcSMN</m> <E>pan.<e><q>","tokens":[{"orig":"וַ","morphs":"Cc","num":"1","notrans":"s/t"},{"orig":"יִּקְרָא","strongs":"H7121","morphs":"VqAmSM3","es":"Trajo","num":"2"},{"orig":"רָעָב","strongs":"H7458","morphs":"NCcSMN","es":"hambre","num":"3"},{"orig":"עַל־","strongs":"H5921","morphs":"Pu","es":"sobre","num":"4"},{"orig":"הָ","morphs":"XD","es":"la","num":"5"},{"orig":"אָרֶץ","strongs":"H776","morphs":"NCcSFPH","es":["tierra,","Y"],"num":"6"},{"orig":"שָׁבָר","strongs":"H7665","morphs":"VqAsSM3","es":"quebrantó","num":"10"},{"orig":"כָּל־","strongs":"H3605","morphs":"NCACCC","es":"todo","num":"7"},{"orig":"מַטֵּה־","strongs":"H4294","morphs":"NCcSMC","es":"sustento","num":"8","added":"← de","marks":"←"},{"orig":"לֶחֶם","strongs":"H3899","morphs":"NCcSMN","es":"pan.","num":"9"}]},"17":{"raw":"<Q><l>שָׁלַח</l><n>1</n> <s>H7971</s> <m>VqAsSM3</m> <E>Envió<e> <E>un<e><q> <Q><l>אִישׁ</l><n>5</n> <s>H376</s> <m>NCcSMN</m> <E>varón<e><q> <Q><l>פְנֵי</l><n>3</n> <s>H6440</s> <m>NCcPMS</m> <E>delante<e><q> <Q><l>לִ</l><n>2</n> <m>PL</m> <E>de<e><q> <Q><l>הֶם</l><n>4</n> <m>RBPM3</m> <E>ellos;<e><q> <Q><l>לְ</l><n>6</n> <m>PL</m> <E>A<e><q> <Q><l>יוֹסֵף</l><n>9</n> <s>H3130</s> <m>NPHSMN</m> <E>José,<e> <E>que<e> <x><f>→</f>fue</x><q> <Q><l>נִמְכַּר</l><n>8</n> <s>H4376</s> <m>VnPsSM3</m> <E>vendido<e> <E>por<e><q> <Q><l>עֶבֶד</l><n>7</n> <s>H5650</s> <m>NCcSMN</m> <E>siervo.<e><q>","tokens":[{"orig":"שָׁלַח","strongs":"H7971","morphs":"VqAsSM3","es":["Envió","un"],"num":"1"},{"orig":"אִישׁ","strongs":"H376","morphs":"NCcSMN","es":"varón","num":"5"},{"orig":"פְנֵי","strongs":"H6440","morphs":"NCcPMS","es":"delante","num":"3"},{"orig":"לִ","morphs":"PL","es":"de","num":"2"},{"orig":"הֶם","morphs":"RBPM3","es":"ellos;","num":"4"},{"orig":"לְ","morphs":"PL","es":"A","num":"6"},{"orig":"יוֹסֵף","strongs":"H3130","morphs":"NPHSMN","es":["José,","que"],"num":"9","added":"→fue","marks":"→"},{"orig":"נִמְכַּר","strongs":"H4376","morphs":"VnPsSM3","es":["vendido","por"],"num":"8"},{"orig":"עֶבֶד","strongs":"H5650","morphs":"NCcSMN","es":"siervo.","num":"7"}]},"18":{"raw":"<Q><l>עִנּוּ</l><n>1</n> <s>H6031</s> <m>VpAsPM3</m> <E>Afligieron<e><q> <Q><l>ו</l><n>6</n> <m>RBSM3</m> <E>sus<e><q> <Q><l>רַגְלָי</l><n>5</n> <s>H7272</s> <m>NCcDFS</m> <E>pies<e><q> <Q><l>ב</l><n>2</n> <m>PB</m> <E>con<e><q> <Q><l>ַ</l><n>3</n> <m>XD</m> <z>s/t</z><q> <Q><l>כֶּבֶל</l><n>4</n> <s>H3525</s> <m>NCcSMNh</m> <E>grillos;<e> <E>En<e><q> <Q><l>בַּרְזֶל</l><n>7</n> <s>H1270</s> <m>NCcSMN</m> <E>cárcel<e> <x><f>→</f>fue</x><q> <Q><l>בָּאָה</l><n>8</n> <s>H935</s> <m>VqAsSF3</m> <E>puesta<e><q> <Q><l>ֹו</l><n>10</n> <m>RBSM3</m> <E>su<e><q> <Q><l>נַפְשׁ</l><n>9</n> <s>H5315</s> <m>NCcSFS</m> <E>persona.<e><q>","tokens":[{"orig":"עִנּוּ","strongs":"H6031","morphs":"VpAsPM3","es":"Afligieron","num":"1"},{"orig":"ו","morphs":"RBSM3","es":"sus","num":"6"},{"orig":"רַגְלָי","strongs":"H7272","morphs":"NCcDFS","es":"pies","num":"5"},{"orig":"ב","morphs":"PB","es":"con","num":"2"},{"orig":"ַ","morphs":"XD","num":"3","notrans":"s/t"},{"orig":"כֶּבֶל","strongs":"H3525","morphs":"NCcSMNh","es":["grillos;","En"],"num":"4"},{"orig":"בַּרְזֶל","strongs":"H1270","morphs":"NCcSMN","es":"cárcel","num":"7","added":"→fue","marks":"→"},{"orig":"בָּאָה","strongs":"H935","morphs":"VqAsSF3","es":"puesta","num":"8"},{"orig":"ֹו","morphs":"RBSM3","es":"su","num":"10"},{"orig":"נַפְשׁ","strongs":"H5315","morphs":"NCcSFS","es":"persona.","num":"9"}]},"19":{"raw":"<Q><l>עַד־</l><n>1</n> <s>H5704</s> <m>PD</m> <E>Hasta<e> <E>la<e><q> <Q><l>עֵת</l><n>2</n> <s>H6256</s> <m>NCcSCC</m> <E>hora<e> <E>que<e> <x><f>→</f>se</x><q> <Q><l>בֹּא־</l><n>3</n> <s>H935</s> <m>VqAT---C</m> <E>cumplió<e><q> <Q><l>ֹו</l><n>5</n> <m>RBSM3</m> <E>su<e><q> <Q><l>דְבָר</l><n>4</n> <s>H1697</s> <m>NCcSMS</m> <E>palabra,<e> <x><f>→</f>El</x><q> <Q><l>אִמְרַת</l><n>6</n> <s>H565</s> <m>NCcSFC</m> <E>dicho<e> <x><f> ← </f>de</x><q> <Q><l>יהוה</l><n>7</n> <s>H3068</s> <m>NPDSMN</m> <E>Jehová<e><q> <Q><l>ְהוּ</l><n>9</n> <m>RBSM3</m> <E>le<e><q> <Q><l>צְרָפָת</l><n>8</n> <s>H6884</s> <m>VqAsSF3</m> <E>probó.<e><q>","tokens":[{"orig":"עַד־","strongs":"H5704","morphs":"PD","es":["Hasta","la"],"num":"1"},{"orig":"עֵת","strongs":"H6256","morphs":"NCcSCC","es":["hora","que"],"num":"2","added":"→se","marks":"→"},{"orig":"בֹּא־","strongs":"H935","morphs":"VqAT---C","es":"cumplió","num":"3"},{"orig":"ֹו","morphs":"RBSM3","es":"su","num":"5"},{"orig":"דְבָר","strongs":"H1697","morphs":"NCcSMS","es":"palabra,","num":"4","added":"→El","marks":"→"},{"orig":"אִמְרַת","strongs":"H565","morphs":"NCcSFC","es":"dicho","num":"6","added":"← de","marks":"←"},{"orig":"יהוה","strongs":"H3068","morphs":"NPDSMN","es":"Jehová","num":"7"},{"orig":"ְהוּ","morphs":"RBSM3","es":"le","num":"9"},{"orig":"צְרָפָת","strongs":"H6884","morphs":"VqAsSF3","es":"probó.","num":"8"}]},"20":{"raw":"<Q><l>שָׁלַח</l><n>1</n> <s>H7971</s> <m>VqAsSM3</m> <E>Envió<e> <E>el<e><q> <Q><l>מֶלֶךְ</l><n>2</n> <s>H4428</s> <m>NCcSMN</m> <E>rey,<e><q> <Q><l>וַ</l><n>3</n> <m>Cc</m> <E>y<e><q> <Q><l>ֵהוּ</l><n>5</n> <m>RBSM3</m> <E>le<e><q> <Q><l>יַּתִּיר</l><n>4</n> <s>H5425</s> <m>VhAmSM3</m> <E>soltó;<e> <x><f>→</f>El</x><q> <Q><l>מֹשֵׁל</l><n>6</n> <s>H4910</s> <m>VqApSM-N</m> <E>señor<e> <x><f> ← </f>de</x> <E>los<e><q> <Q><l>עַמִּים</l><n>7</n> <s>H5971</s> <m>NCcPMN</m> <E>pueblos,<e><q> <Q><l>וַ</l><n>8</n> <m>Cc</m> <E>y<e><q> <Q><l>ֵהוּ</l><n>10</n> <m>RBSM3</m> <E>le<e><q> <Q><l>יְפַתְּח</l><n>9</n> <s>H6605</s> <m>VpAmSM3</m> <E>dejó<e> <x><f> ← </f>ir</x> <x><f> ← </f>libre.</x>","tokens":[{"orig":"שָׁלַח","strongs":"H7971","morphs":"VqAsSM3","es":["Envió","el"],"num":"1"},{"orig":"מֶלֶךְ","strongs":"H4428","morphs":"NCcSMN","es":"rey,","num":"2"},{"orig":"וַ","morphs":"Cc","es":"y","num":"3"},{"orig":"ֵהוּ","morphs":"RBSM3","es":"le","num":"5"},{"orig":"יַּתִּיר","strongs":"H5425","morphs":"VhAmSM3","es":"soltó;","num":"4","added":"→El","marks":"→"},{"orig":"מֹשֵׁל","strongs":"H4910","morphs":"VqApSM-N","es":["señor","los"],"num":"6","added":"← de","marks":"←"},{"orig":"עַמִּים","strongs":"H5971","morphs":"NCcPMN","es":"pueblos,","num":"7"},{"orig":"וַ","morphs":"Cc","es":"y","num":"8"},{"orig":"ֵהוּ","morphs":"RBSM3","es":"le","num":"10"},{"orig":"יְפַתְּח","strongs":"H6605","morphs":"VpAmSM3","es":"dejó","num":"9","added":["← ir","← libre."],"marks":["←","←"]}]},"21":{"raw":"<Q><l>ו</l><n>2</n> <m>RBSM3</m> <E>Lo<e><q> <Q><l>שָׂמ</l><n>1</n> <s>H7760</s> <m>VqAsSM3</m> <E>puso<e> <E>por<e><q> <Q><l>אָדוֹן</l><n>3</n> <s>H113</s> <m>NCcSMN</m> <E>señor<e><q> <Q><l>לְ</l><n>4</n> <m>PL</m> <E>de<e><q> <Q><l>ֹו</l><n>6</n> <m>RBSM3</m> <E>su<e><q> <Q><l>בֵית</l><n>5</n> <s>H1004</s> <m>NCcSMS</m> <E>casa,<e><q> <Q><l>וּ</l><n>7</n> <m>CC</m> <E>Y<e> <E>por<e><q> <Q><l>מֹשֵׁל</l><n>8</n> <s>H4910</s> <m>VqAtSM-N</m> <E>gobernador<e><q> <Q><l>בְּ</l><n>9</n> <m>PB</m> <E>de<e><q> <Q><l>כָל־</l><n>10</n> <s>H3605</s> <m>NCACCC</m> <E>todas<e><q> <Q><l>ֹו</l><n>12</n> <m>RBSM3</m> <E>sus<e><q> <Q><l>קִנְיָנ</l><n>11</n> <s>H7075</s> <m>NCcSMS</m> <E>posesiones,<e><q>","tokens":[{"orig":"ו","morphs":"RBSM3","es":"Lo","num":"2"},{"orig":"שָׂמ","strongs":"H7760","morphs":"VqAsSM3","es":["puso","por"],"num":"1"},{"orig":"אָדוֹן","strongs":"H113","morphs":"NCcSMN","es":"señor","num":"3"},{"orig":"לְ","morphs":"PL","es":"de","num":"4"},{"orig":"ֹו","morphs":"RBSM3","es":"su","num":"6"},{"orig":"בֵית","strongs":"H1004","morphs":"NCcSMS","es":"casa,","num":"5"},{"orig":"וּ","morphs":"CC","es":["Y","por"],"num":"7"},{"orig":"מֹשֵׁל","strongs":"H4910","morphs":"VqAtSM-N","es":"gobernador","num":"8"},{"orig":"בְּ","morphs":"PB","es":"de","num":"9"},{"orig":"כָל־","strongs":"H3605","morphs":"NCACCC","es":"todas","num":"10"},{"orig":"ֹו","morphs":"RBSM3","es":"sus","num":"12"},{"orig":"קִנְיָנ","strongs":"H7075","morphs":"NCcSMS","es":"posesiones,","num":"11"}]},"22":{"raw":"<Q><l>לֶ</l><n>1</n> <m>PL</m> <E>Para<e> <E>que<e><q> <Q><l>אְסֹר</l><n>2</n> <s>H631</s> <m>VqAT---C</m> <E>reprimiera<e> <E>a<e><q> <Q><l>ו</l><n>4</n> <m>RBSM3</m> <E>sus<e><q> <Q><l>שָׂרָי</l><n>3</n> <s>H8269</s> <m>NCcPMS</m> <E>grandes<e><q> <Q><l>בְּ</l><n>5</n> <m>PB</m> <E>como<e><q> <Q><l>ֹו</l><n>7</n> <m>RBSM3</m> <E>él<e><q> <Q><l>נַפְשׁ</l><n>6</n> <s>H5315</s> <m>NCcSFS</m> <E>quisiese,<e><q> <Q><l>וּ</l><n>8</n> <m>CC</m> <E>Y<e> <E>a<e><q> <Q><l>ו</l><n>10</n> <m>RBSM3</m> <E>sus<e><q> <Q><l>זְקֵנָי</l><n>9</n> <s>H2205</s> <m>NCcPMS</m> <E>ancianos<e> <x><f>→</f>enseñara</x><q> <Q><l>יְחַכֵּם</l><n>11</n> <s>H2449</s> <m>VpAMSM3</m> <E>sabiduría.<e><q>","tokens":[{"orig":"לֶ","morphs":"PL","es":["Para","que"],"num":"1"},{"orig":"אְסֹר","strongs":"H631","morphs":"VqAT---C","es":["reprimiera","a"],"num":"2"},{"orig":"ו","morphs":"RBSM3","es":"sus","num":"4"},{"orig":"שָׂרָי","strongs":"H8269","morphs":"NCcPMS","es":"grandes","num":"3"},{"orig":"בְּ","morphs":"PB","es":"como","num":"5"},{"orig":"ֹו","morphs":"RBSM3","es":"él","num":"7"},{"orig":"נַפְשׁ","strongs":"H5315","morphs":"NCcSFS","es":"quisiese,","num":"6"},{"orig":"וּ","morphs":"CC","es":["Y","a"],"num":"8"},{"orig":"ו","morphs":"RBSM3","es":"sus","num":"10"},{"orig":"זְקֵנָי","strongs":"H2205","morphs":"NCcPMS","es":"ancianos","num":"9","added":"→enseñara","marks":"→"},{"orig":"יְחַכֵּם","strongs":"H2449","morphs":"VpAMSM3","es":"sabiduría.","num":"11"}]},"23":{"raw":"<Q><l>וַ</l><n>1</n> <m>Cc</m> <E>Después<e><q> <Q><l>יָּבֹא</l><n>2</n> <s>H935</s> <m>VqAmSM3</m> <E>entró<e><q> <Q><l>יִשְׂרָאֵל</l><n>3</n> <s>H3478</s> <m>NPHSMN</m> <E>Israel<e> <E>en<e><q> <Q><l>מִצְרָיִם</l><n>4</n> <s>H4714</s> <m>NPLSFP</m> <E>Egipto,<e><q> <Q><l>וְ</l><n>5</n> <m>CC</m> <E>Y<e><q> <Q><l>יַעֲקֹב</l><n>6</n> <s>H3290</s> <m>NPHSMN</m> <E>Jacob<e><q> <Q><l>גָּר</l><n>7</n> <s>H1481</s> <m>VqAsSM3</m> <E>moró<e><q> <Q><l>בְּ</l><n>8</n> <m>PB</m> <E>en<e> <x><f>→</f>la</x><q> <Q><l>אֶרֶץ־</l><n>9</n> <s>H776</s> <m>NCcSFC</m> <E>tierra<e> <x><f> ← </f>de</x><q> <Q><l>חָם</l><n>10</n> <s>H2526</s> <m>NPHSMN</m> <E>Cam.<e><q>","tokens":[{"orig":"וַ","morphs":"Cc","es":"Después","num":"1"},{"orig":"יָּבֹא","strongs":"H935","morphs":"VqAmSM3","es":"entró","num":"2"},{"orig":"יִשְׂרָאֵל","strongs":"H3478","morphs":"NPHSMN","es":["Israel","en"],"num":"3"},{"orig":"מִצְרָיִם","strongs":"H4714","morphs":"NPLSFP","es":"Egipto,","num":"4"},{"orig":"וְ","morphs":"CC","es":"Y","num":"5"},{"orig":"יַעֲקֹב","strongs":"H3290","morphs":"NPHSMN","es":"Jacob","num":"6"},{"orig":"גָּר","strongs":"H1481","morphs":"VqAsSM3","es":"moró","num":"7"},{"orig":"בְּ","morphs":"PB","es":"en","num":"8","added":"→la","marks":"→"},{"orig":"אֶרֶץ־","strongs":"H776","morphs":"NCcSFC","es":"tierra","num":"9","added":"← de","marks":"←"},{"orig":"חָם","strongs":"H2526","morphs":"NPHSMN","es":"Cam.","num":"10"}]},"24":{"raw":"<Q><l>וַ</l><n>1</n> <m>Cc</m> <E>Y<e><q> <Q><l>יֶּפֶר</l><n>2</n> <s>H6509</s> <m>VhAmSM3</m> <E>multiplicó<e><q> <Q><l>אֶת־</l><n>3</n> <s>H853</s> <m>PA</m> <z>s/t</z><q> <Q><l>ֹו</l><n>5</n> <m>RBSM3</m> <E>su<e><q> <Q><l>עַמּ</l><n>4</n> <s>H5971</s> <m>NCcSMS</m> <E>pueblo<e> <x><f>→</f>en</x><q> <Q><l>מְאֹד</l><n>6</n> <s>H3966</s> <m>Av</m> <E>gran<e> <x><f> ← </f>manera,</x><q> <Q><l>וַ</l><n>7</n> <m>Cc</m> <E>Y<e><q> <Q><l>ֵהוּ</l><n>9</n> <m>RBSM3</m> <E>lo<e> <f>►8</f> <E>hizo<e> <E>más<e><q> <Q><l>יַּעֲצִמ</l><n>8</n> <s>H6105</s> <m>VhAmSM3</m> <E>fuerte<e><q> <Q><l>מִ</l><n>10</n> <m>PM</m> <E>que<e><q> <Q><l>ו</l><n>12</n> <m>RBSM3</m> <E>sus<e><q> <Q><l>צָּרָי</l><n>11</n> <s>H6862</s> <m>NCcPMS</m> <E>enemigos.<e><q>","tokens":[{"orig":"וַ","morphs":"Cc","es":"Y","num":"1"},{"orig":"יֶּפֶר","strongs":"H6509","morphs":"VhAmSM3","es":"multiplicó","num":"2"},{"orig":"אֶת־","strongs":"H853","morphs":"PA","num":"3","notrans":"s/t"},{"orig":"ֹו","morphs":"RBSM3","es":"su","num":"5"},{"orig":"עַמּ","strongs":"H5971","morphs":"NCcSMS","es":"pueblo","num":"4","added":"→en","marks":"→"},{"orig":"מְאֹד","strongs":"H3966","morphs":"Av","es":"gran","num":"6","added":"← manera,","marks":"←"},{"orig":"וַ","morphs":"Cc","es":"Y","num":"7"},{"orig":"ֵהוּ","morphs":"RBSM3","es":["lo","hizo","más"],"num":"9","marks":"►8"},{"orig":"יַּעֲצִמ","strongs":"H6105","morphs":"VhAmSM3","es":"fuerte","num":"8"},{"orig":"מִ","morphs":"PM","es":"que","num":"10"},{"orig":"ו","morphs":"RBSM3","es":"sus","num":"12"},{"orig":"צָּרָי","strongs":"H6862","morphs":"NCcPMS","es":"enemigos.","num":"11"}]},"25":{"raw":"<Q><l>הָפַךְ</l><n>1</n> <s>H2015</s> <m>VqAsSM3</m> <E>Cambió<e> <x><f>→</f>el</x><q> <Q><l>לִבּ</l><n>2</n> <s>H3820</s> <m>NCcSMS</m> <E>corazón<e> <x><f> ← </f>de</x><q> <Q><l>ָם</l><n>3</n> <m>RBPM3</m> <E>ellos<e><q> <Q><l>לִ</l><n>4</n> <m>PL</m> <E>para<e> <E>que<e><q> <Q><l>שְׂנֹא</l><n>5</n> <s>H8130</s> <m>VqAT---C</m> <E>aborreciesen<e> <E>a<e><q> <Q><l>ֹו</l><n>7</n> <m>RBSM3</m> <E>su<e><q> <Q><l>עַמּ</l><n>6</n> <s>H5971</s> <m>NCcSMS</m> <E>pueblo,<e><q> <Q><l>לְ</l><n>8</n> <m>PL</m> <E>Para<e> <E>que<e><q> <Q><l>בַּ</l><n>10</n> <m>PB</m> <E>contra<e><q> <Q><l>ו</l><n>12</n> <m>RBSM3</m> <E>sus<e><q> <Q><l>עֲבָדָי</l><n>11</n> <s>H5650</s> <m>NCcPMS</m> <E>siervos<e><q> <Q><l>הִתְנַכֵּל</l><n>9</n> <s>H5230</s> <m>VtMT---C</m> <E>pensasen<e> <x><f> ← </f>mal.</x>","tokens":[{"orig":"הָפַךְ","strongs":"H2015","morphs":"VqAsSM3","es":"Cambió","num":"1","added":"→el","marks":"→"},{"orig":"לִבּ","strongs":"H3820","morphs":"NCcSMS","es":"corazón","num":"2","added":"← de","marks":"←"},{"orig":"ָם","morphs":"RBPM3","es":"ellos","num":"3"},{"orig":"לִ","morphs":"PL","es":["para","que"],"num":"4"},{"orig":"שְׂנֹא","strongs":"H8130","morphs":"VqAT---C","es":["aborreciesen","a"],"num":"5"},{"orig":"ֹו","morphs":"RBSM3","es":"su","num":"7"},{"orig":"עַמּ","strongs":"H5971","morphs":"NCcSMS","es":"pueblo,","num":"6"},{"orig":"לְ","morphs":"PL","es":["Para","que"],"num":"8"},{"orig":"בַּ","morphs":"PB","es":"contra","num":"10"},{"orig":"ו","morphs":"RBSM3","es":"sus","num":"12"},{"orig":"עֲבָדָי","strongs":"H5650","morphs":"NCcPMS","es":"siervos","num":"11"},{"orig":"הִתְנַכֵּל","strongs":"H5230","morphs":"VtMT---C","es":"pensasen","num":"9","added":"← mal.","marks":"←"}]},"26":{"raw":"<Q><l>שָׁלַח</l><n>1</n> <s>H7971</s> <m>VqAsSM3</m> <E>Envió<e> <E>a<e><q> <Q><l>ֹו</l><n>4</n> <m>RBSM3</m> <E>su<e><q> <Q><l>עַבְדּ</l><n>3</n> <s>H5650</s> <m>NCcSMS</m> <E>siervo<e><q> <Q><l>מֹשֶׁה</l><n>2</n> <s>H4872</s> <m>NPHSMN</m> <E>Moisés,<e> <E>Y<e> <E>a<e><q> <Q><l>אַהֲרֹן</l><n>5</n> <s>H175</s> <m>NPHSMN</m> <E>Aarón,<e><q> <Q><l>אֲשֶׁר</l><n>6</n> <s>H834</s> <m>XN</m> <z>s/t</z><q> <Q><l>בּ</l><n>8</n> <m>PB</m> <E>al<e><q> <Q><l>ֹו</l><n>9</n> <m>RBSM3</m> <E>cual<e><q> <Q><l>בָּחַר־</l><n>7</n> <s>H977</s> <m>VqAsSM3</m> <E>escogió.<e><q>","tokens":[{"orig":"שָׁלַח","strongs":"H7971","morphs":"VqAsSM3","es":["Envió","a"],"num":"1"},{"orig":"ֹו","morphs":"RBSM3","es":"su","num":"4"},{"orig":"עַבְדּ","strongs":"H5650","morphs":"NCcSMS","es":"siervo","num":"3"},{"orig":"מֹשֶׁה","strongs":"H4872","morphs":"NPHSMN","es":["Moisés,","Y","a"],"num":"2"},{"orig":"אַהֲרֹן","strongs":"H175","morphs":"NPHSMN","es":"Aarón,","num":"5"},{"orig":"אֲשֶׁר","strongs":"H834","morphs":"XN","num":"6","notrans":"s/t"},{"orig":"בּ","morphs":"PB","es":"al","num":"8"},{"orig":"ֹו","morphs":"RBSM3","es":"cual","num":"9"},{"orig":"בָּחַר־","strongs":"H977","morphs":"VqAsSM3","es":"escogió.","num":"7"}]},"27":{"raw":"<Q><l>שָׂמוּ־</l><n>1</n> <s>H7760</s> <m>VqAsPC3</m> <E>Puso<e><q> <Q><l>ב</l><n>2</n> <m>PB</m> <E>en<e><q> <Q><l>ָם</l><n>3</n> <m>RBPM3</m> <E>ellos<e> <x><f>→</f>las</x><q> <Q><l>דִּבְרֵי</l><n>4</n> <s>H1697</s> <m>NCcPMC</m> <E>palabras<e> <x><f> ← </f>de</x><q> <Q><l>ו</l><n>6</n> <m>RBSM3</m> <E>sus<e><q> <Q><l>אֹתוֹתָי</l><n>5</n> <s>H226</s> <m>NCcPMS</m> <E>señales,<e><q> <Q><l>וּ</l><n>7</n> <m>CC</m> <E>Y<e> <E>sus<e><q> <Q><l>מֹפְתִים</l><n>8</n> <s>H4159</s> <m>NCcPMN</m> <E>prodigios<e><q> <Q><l>בְּ</l><n>9</n> <m>PB</m> <E>en<e> <x><f>→</f>la</x><q> <Q><l>אֶרֶץ</l><n>10</n> <s>H776</s> <m>NCcSFC</m> <E>tierra<e> <x><f> ← </f>de</x><q> <Q><l>חָם</l><n>11</n> <s>H2526</s> <m>NPHSMN</m> <E>Cam.<e><q>","tokens":[{"orig":"שָׂמוּ־","strongs":"H7760","morphs":"VqAsPC3","es":"Puso","num":"1"},{"orig":"ב","morphs":"PB","es":"en","num":"2"},{"orig":"ָם","morphs":"RBPM3","es":"ellos","num":"3","added":"→las","marks":"→"},{"orig":"דִּבְרֵי","strongs":"H1697","morphs":"NCcPMC","es":"palabras","num":"4","added":"← de","marks":"←"},{"orig":"ו","morphs":"RBSM3","es":"sus","num":"6"},{"orig":"אֹתוֹתָי","strongs":"H226","morphs":"NCcPMS","es":"señales,","num":"5"},{"orig":"וּ","morphs":"CC","es":["Y","sus"],"num":"7"},{"orig":"מֹפְתִים","strongs":"H4159","morphs":"NCcPMN","es":"prodigios","num":"8"},{"orig":"בְּ","morphs":"PB","es":"en","num":"9","added":"→la","marks":"→"},{"orig":"אֶרֶץ","strongs":"H776","morphs":"NCcSFC","es":"tierra","num":"10","added":"← de","marks":"←"},{"orig":"חָם","strongs":"H2526","morphs":"NPHSMN","es":"Cam.","num":"11"}]},"28":{"raw":"<Q><l>שָׁלַח</l><n>1</n> <s>H7971</s> <m>VqAsSM3</m> <E>Envió<e><q> <Q><l>חֹשֶׁךְ</l><n>2</n> <s>H2822</s> <m>NCcSMN</m> <E>tinieblas<e><q> <Q><l>וַ</l><n>3</n> <m>Cc</m> <E>que<e> <E>lo<e><q> <Q><l>יַּחְשִׁךְ</l><n>4</n> <s>H2822</s> <m>VhAmSM3</m> <E>oscurecieron<e> <E>todo;<e><q> <Q><l>וְ</l><n>5</n> <m>CC</m> <z>s/t</z><q> <Q><l>לֹא־</l><n>6</n> <s>H3808</s> <m>ANN</m> <E>No<e> <x><f>→</f>fueron</x><q> <Q><l>מָרוּ</l><n>7</n> <s>H4784</s> <m>VqAsPM3</m> <E>rebeldes<e><q> <Q><l>אֶת־</l><n>8</n> <m>PA</m> <E>a<e><q> <Q><l>ו</l><n>10</n> <m>RBSM3</m> <E>su<e><q> <Q><l>דְּבָרָי</l><n>9</n> <m>NCcPMS</m> <E>palabra.<e><q>","tokens":[{"orig":"שָׁלַח","strongs":"H7971","morphs":"VqAsSM3","es":"Envió","num":"1"},{"orig":"חֹשֶׁךְ","strongs":"H2822","morphs":"NCcSMN","es":"tinieblas","num":"2"},{"orig":"וַ","morphs":"Cc","es":["que","lo"],"num":"3"},{"orig":"יַּחְשִׁךְ","strongs":"H2822","morphs":"VhAmSM3","es":["oscurecieron","todo;"],"num":"4"},{"orig":"וְ","morphs":"CC","num":"5","notrans":"s/t"},{"orig":"לֹא־","strongs":"H3808","morphs":"ANN","es":"No","num":"6","added":"→fueron","marks":"→"},{"orig":"מָרוּ","strongs":"H4784","morphs":"VqAsPM3","es":"rebeldes","num":"7"},{"orig":"אֶת־","morphs":"PA","es":"a","num":"8"},{"orig":"ו","morphs":"RBSM3","es":"su","num":"10"},{"orig":"דְּבָרָי","morphs":"NCcPMS","es":"palabra.","num":"9"}]},"29":{"raw":"<Q><l>הָפַךְ</l><n>1</n> <s>H2015</s> <m>VqAsSM3</m> <E>Volvió<e><q> <Q><l>אֶת־</l><n>2</n> <s>H853</s> <m>PA</m> <z>s/t</z><q> <Q><l>הֶם</l><n>4</n> <m>RBPM3</m> <E>sus<e><q> <Q><l>מֵימֵי</l><n>3</n> <s>H4325</s> <m>NCcPMS</m> <E>aguas<e><q> <Q><l>לְ</l><n>5</n> <m>PL</m> <E>en<e><q> <Q><l>דָם</l><n>6</n> <s>H1818</s> <m>NCcSMN</m> <E>sangre,<e><q> <Q><l>וַ</l><n>7</n> <m>Cc</m> <E>Y<e><q> <Q><l>יָּמֶת</l><n>8</n> <s>H4191</s> <m>VhAmSM3</m> <E>mató<e><q> <Q><l>אֶת־</l><n>9</n> <s>H853</s> <m>PA</m> <z>s/t</z><q> <Q><l>ָם</l><n>11</n> <m>RBPM3</m> <E>sus<e><q> <Q><l>דְּגָת</l><n>10</n> <s>H1710</s> <m>NCcSFS</m> <E>peces.<e><q>","tokens":[{"orig":"הָפַךְ","strongs":"H2015","morphs":"VqAsSM3","es":"Volvió","num":"1"},{"orig":"אֶת־","strongs":"H853","morphs":"PA","num":"2","notrans":"s/t"},{"orig":"הֶם","morphs":"RBPM3","es":"sus","num":"4"},{"orig":"מֵימֵי","strongs":"H4325","morphs":"NCcPMS","es":"aguas","num":"3"},{"orig":"לְ","morphs":"PL","es":"en","num":"5"},{"orig":"דָם","strongs":"H1818","morphs":"NCcSMN","es":"sangre,","num":"6"},{"orig":"וַ","morphs":"Cc","es":"Y","num":"7"},{"orig":"יָּמֶת","strongs":"H4191","morphs":"VhAmSM3","es":"mató","num":"8"},{"orig":"אֶת־","strongs":"H853","morphs":"PA","num":"9","notrans":"s/t"},{"orig":"ָם","morphs":"RBPM3","es":"sus","num":"11"},{"orig":"דְּגָת","strongs":"H1710","morphs":"NCcSFS","es":"peces.","num":"10"}]},"30":{"raw":"<Q><l>ָם</l><n>3</n> <m>RBPM3</m> <E>Su<e><q> <Q><l>אַרְצ</l><n>2</n> <s>H776</s> <m>NCcSFS</m> <E>tierra<e><q> <Q><l>שָׁרַץ</l><n>1</n> <s>H8317</s> <m>VqAsSM3</m> <E>produjo<e><q> <Q><l>צְפַרְדְּעִים</l><n>4</n> <s>H6854</s> <m>NCcPMN</m> <E>ranas<e> <E>Hasta<e><q> <Q><l>בְּ</l><n>5</n> <m>PB</m> <E>en<e> <x><f>→</f>las</x><q> <Q><l>חַדְרֵי</l><n>6</n> <s>H2315</s> <m>NCcPMC</m> <E>cámaras<e> <x><f> ← </f>de</x><q> <Q><l>הֶם</l><n>8</n> <m>RBPM3</m> <E>sus<e><q> <Q><l>מַלְכֵי</l><n>7</n> <s>H4428</s> <m>NCcPMS</m> <E>reyes.<e><q>","tokens":[{"orig":"ָם","morphs":"RBPM3","es":"Su","num":"3"},{"orig":"אַרְצ","strongs":"H776","morphs":"NCcSFS","es":"tierra","num":"2"},{"orig":"שָׁרַץ","strongs":"H8317","morphs":"VqAsSM3","es":"produjo","num":"1"},{"orig":"צְפַרְדְּעִים","strongs":"H6854","morphs":"NCcPMN","es":["ranas","Hasta"],"num":"4"},{"orig":"בְּ","morphs":"PB","es":"en","num":"5","added":"→las","marks":"→"},{"orig":"חַדְרֵי","strongs":"H2315","morphs":"NCcPMC","es":"cámaras","num":"6","added":"← de","marks":"←"},{"orig":"הֶם","morphs":"RBPM3","es":"sus","num":"8"},{"orig":"מַלְכֵי","strongs":"H4428","morphs":"NCcPMS","es":"reyes.","num":"7"}]},"31":{"raw":"<Q><l>אָמַר</l><n>1</n> <s>H559</s> <m>VqAsSM3</m> <E>Habló,<e><q> <Q><l>וַ</l><n>2</n> <m>Cc</m> <E>y<e><q> <Q><l>יָּבֹא</l><n>3</n> <s>H935</s> <m>VqAmSM3</m> <E>vinieron<e> <x><f>→</f>enjambres</x> <x><f>→</f>de</x><q> <Q><l>עָרֹב</l><n>4</n> <s>H6157</s> <m>NCcSMN</m> <E>moscas,<e> <E>Y<e><q> <Q><l>כִּנִּים</l><n>5</n> <s>H3654</s> <m>NCcPMN</m> <E>piojos<e><q> <Q><l>בְּ</l><n>6</n> <m>PB</m> <E>en<e><q> <Q><l>כָל־</l><n>7</n> <s>H3605</s> <m>NCACCC</m> <E>todos<e><q> <Q><l>ָם</l><n>9</n> <m>RBPM3</m> <E>sus<e><q> <Q><l>גְּבוּל</l><n>8</n> <s>H1366</s> <m>NCcSMS</m> <E>términos.<e><q>","tokens":[{"orig":"אָמַר","strongs":"H559","morphs":"VqAsSM3","es":"Habló,","num":"1"},{"orig":"וַ","morphs":"Cc","es":"y","num":"2"},{"orig":"יָּבֹא","strongs":"H935","morphs":"VqAmSM3","es":"vinieron","num":"3","added":["→enjambres","→de"],"marks":["→","→"]},{"orig":"עָרֹב","strongs":"H6157","morphs":"NCcSMN","es":["moscas,","Y"],"num":"4"},{"orig":"כִּנִּים","strongs":"H3654","morphs":"NCcPMN","es":"piojos","num":"5"},{"orig":"בְּ","morphs":"PB","es":"en","num":"6"},{"orig":"כָל־","strongs":"H3605","morphs":"NCACCC","es":"todos","num":"7"},{"orig":"ָם","morphs":"RBPM3","es":"sus","num":"9"},{"orig":"גְּבוּל","strongs":"H1366","morphs":"NCcSMS","es":"términos.","num":"8"}]},"32":{"raw":"<E>Les<e><q> <Q><l>נָתַן</l><n>1</n> <s>H5414</s> <m>VqAsSM3</m> <E>dio<e><q> <Q><l>בָּרָד</l><n>4</n> <s>H1259</s> <m>NCcSMN</m> <E>granizo<e> <E>por<e><q> <Q><l>גִּשְׁמֵי</l><n>2</n> <s>H1653</s> <m>NCcPMS</m> <E>lluvia,<e><q> <Q><l>הֶם</l><n>3</n> <m>RBPM3</m> <z>s/t</z> <E>Y<e><q> <Q><l>לֶהָבוֹת</l><n>6</n> <s>H3852</s> <m>NCcPFN</m> <E>llamas<e> <x><f> ← </f>de</x><q> <Q><l>אֵשׁ</l><n>5</n> <s>H784</s> <m>NCcSFC</m> <E>fuego<e><q> <Q><l>בְּ</l><n>7</n> <m>PB</m> <E>en<e><q> <Q><l>ָם</l><n>9</n> <m>RBPM3</m> <E>su<e><q> <Q><l>אַרְצ</l><n>8</n> <s>H776</s> <m>NCcSFS</m> <E>tierra.<e><q>","tokens":[{"orig":"נָתַן","strongs":"H5414","morphs":"VqAsSM3","es":"dio","num":"1"},{"orig":"בָּרָד","strongs":"H1259","morphs":"NCcSMN","es":["granizo","por"],"num":"4"},{"orig":"גִּשְׁמֵי","strongs":"H1653","morphs":"NCcPMS","es":"lluvia,","num":"2"},{"orig":"הֶם","morphs":"RBPM3","es":"Y","num":"3","notrans":"s/t"},{"orig":"לֶהָבוֹת","strongs":"H3852","morphs":"NCcPFN","es":"llamas","num":"6","added":"← de","marks":"←"},{"orig":"אֵשׁ","strongs":"H784","morphs":"NCcSFC","es":"fuego","num":"5"},{"orig":"בְּ","morphs":"PB","es":"en","num":"7"},{"orig":"ָם","morphs":"RBPM3","es":"su","num":"9"},{"orig":"אַרְצ","strongs":"H776","morphs":"NCcSFS","es":"tierra.","num":"8"}]},"33":{"raw":"<Q><l>וַ</l><n>1</n> <m>Cc</m> <z>s/t</z><q> <Q><l>יַּךְ</l><n>2</n> <s>H5221</s> <m>VhAmSM3</m> <E>Destrozó<e><q> <Q><l>ָם</l><n>4</n> <m>RBPM3</m> <E>sus<e><q> <Q><l>גַּפְנ</l><n>3</n> <s>H1612</s> <m>NCcSFS</m> <E>viñas<e><q> <Q><l>וּ</l><n>5</n> <m>CC</m> <E>y<e><q> <Q><l>ָם</l><n>7</n> <m>RBPM3</m> <E>sus<e><q> <Q><l>תְאֵנָת</l><n>6</n> <s>H8384</s> <m>NCcSFS</m> <E>higueras,<e><q> <Q><l>וַ</l><n>8</n> <m>Cc</m> <E>Y<e><q> <Q><l>יְשַׁבֵּר</l><n>9</n> <s>H7665</s> <m>VpAmSM3</m> <E>quebró<e> <x><f>→</f>los</x><q> <Q><l>עֵץ</l><n>10</n> <s>H6086</s> <m>NCcSMC</m> <E>árboles<e> <x><f> ← </f>de</x><q> <Q><l>ָם</l><n>12</n> <m>RBPM3</m> <E>su<e><q> <Q><l>גְּבוּל</l><n>11</n> <s>H1366</s> <m>NCcSMS</m> <E>territorio.<e><q>","tokens":[{"orig":"וַ","morphs":"Cc","num":"1","notrans":"s/t"},{"orig":"יַּךְ","strongs":"H5221","morphs":"VhAmSM3","es":"Destrozó","num":"2"},{"orig":"ָם","morphs":"RBPM3","es":"sus","num":"4"},{"orig":"גַּפְנ","strongs":"H1612","morphs":"NCcSFS","es":"viñas","num":"3"},{"orig":"וּ","morphs":"CC","es":"y","num":"5"},{"orig":"ָם","morphs":"RBPM3","es":"sus","num":"7"},{"orig":"תְאֵנָת","strongs":"H8384","morphs":"NCcSFS","es":"higueras,","num":"6"},{"orig":"וַ","morphs":"Cc","es":"Y","num":"8"},{"orig":"יְשַׁבֵּר","strongs":"H7665","morphs":"VpAmSM3","es":"quebró","num":"9","added":"→los","marks":"→"},{"orig":"עֵץ","strongs":"H6086","morphs":"NCcSMC","es":"árboles","num":"10","added":"← de","marks":"←"},{"orig":"ָם","morphs":"RBPM3","es":"su","num":"12"},{"orig":"גְּבוּל","strongs":"H1366","morphs":"NCcSMS","es":"territorio.","num":"11"}]},"34":{"raw":"<Q><l>אָמַר</l><n>1</n> <s>H559</s> <m>VqAsSM3</m> <E>Habló,<e><q> <Q><l>וַ</l><n>2</n> <m>Cc</m> <E>y<e><q> <Q><l>יָּבֹא</l><n>3</n> <s>H935</s> <m>VqAmSM3</m> <E>vinieron<e><q> <Q><l>אַרְבֶּה</l><n>4</n> <s>H697</s> <m>NCcCMN</m> <E>langostas,<e><q> <Q><l>וְ</l><n>5</n> <m>CC</m> <E>Y<e><q> <Q><l>יֶלֶק</l><n>6</n> <s>H3218</s> <m>NCcSMN</m> <E>pulgón<e><q> <Q><l>וְ</l><n>7</n> <m>CC</m> <z>s/t</z><q> <Q><l>אֵין</l><n>8</n> <s>H369</s> <m>AQn</m> <E>sin<e><q> <Q><l>מִסְפָּר</l><n>9</n> <s>H4557</s> <m>NCcSMN</m> <E>número;<e><q>","tokens":[{"orig":"אָמַר","strongs":"H559","morphs":"VqAsSM3","es":"Habló,","num":"1"},{"orig":"וַ","morphs":"Cc","es":"y","num":"2"},{"orig":"יָּבֹא","strongs":"H935","morphs":"VqAmSM3","es":"vinieron","num":"3"},{"orig":"אַרְבֶּה","strongs":"H697","morphs":"NCcCMN","es":"langostas,","num":"4"},{"orig":"וְ","morphs":"CC","es":"Y","num":"5"},{"orig":"יֶלֶק","strongs":"H3218","morphs":"NCcSMN","es":"pulgón","num":"6"},{"orig":"וְ","morphs":"CC","num":"7","notrans":"s/t"},{"orig":"אֵין","strongs":"H369","morphs":"AQn","es":"sin","num":"8"},{"orig":"מִסְפָּר","strongs":"H4557","morphs":"NCcSMN","es":"número;","num":"9"}]},"35":{"raw":"<Q><l>וַ</l><n>1</n> <m>Cc</m> <E>Y<e><q> <Q><l>יֹּאכַל</l><n>2</n> <s>H398</s> <m>VqAmSM3</m> <E>comieron<e><q> <Q><l>כָּל־</l><n>3</n> <s>H398</s> <m>NCACCC</m> <E>toda<e> <E>la<e><q> <Q><l>עֵשֶׂב</l><n>4</n> <s>H6212</s> <m>NCcSMN</m> <E>hierba<e><q> <Q><l>בְּ</l><n>5</n> <m>PB</m> <E>de<e><q> <Q><l>ָם</l><n>7</n> <m>RBPM3</m> <E>su<e><q> <Q><l>אַרְצ</l><n>6</n> <s>H776</s> <m>NCcSFS</m> <E>país,<e><q> <Q><l>וַ</l><n>8</n> <m>Cc</m> <E>Y<e><q> <Q><l>יֹּאכַל</l><n>9</n> <s>H398</s> <m>VqAmSM3</m> <E>devoraron<e> <x><f>→</f>el</x><q> <Q><l>פְּרִי</l><n>10</n> <s>H6529</s> <m>NCcSMC</m> <E>fruto<e> <x><f> ← </f>de</x><q> <Q><l>ָם</l><n>12</n> <m>RBPM3</m> <E>su<e><q> <Q><l>אַדְמָת</l><n>11</n> <s>H127</s> <m>NCcSFS</m> <E>tierra.<e><q>","tokens":[{"orig":"וַ","morphs":"Cc","es":"Y","num":"1"},{"orig":"יֹּאכַל","strongs":"H398","morphs":"VqAmSM3","es":"comieron","num":"2"},{"orig":"כָּל־","strongs":"H398","morphs":"NCACCC","es":["toda","la"],"num":"3"},{"orig":"עֵשֶׂב","strongs":"H6212","morphs":"NCcSMN","es":"hierba","num":"4"},{"orig":"בְּ","morphs":"PB","es":"de","num":"5"},{"orig":"ָם","morphs":"RBPM3","es":"su","num":"7"},{"orig":"אַרְצ","strongs":"H776","morphs":"NCcSFS","es":"país,","num":"6"},{"orig":"וַ","morphs":"Cc","es":"Y","num":"8"},{"orig":"יֹּאכַל","strongs":"H398","morphs":"VqAmSM3","es":"devoraron","num":"9","added":"→el","marks":"→"},{"orig":"פְּרִי","strongs":"H6529","morphs":"NCcSMC","es":"fruto","num":"10","added":"← de","marks":"←"},{"orig":"ָם","morphs":"RBPM3","es":"su","num":"12"},{"orig":"אַדְמָת","strongs":"H127","morphs":"NCcSFS","es":"tierra.","num":"11"}]},"36":{"raw":"<Q><l>וַ</l><n>1</n> <m>Cc</m> <z>s/t</z><q> <Q><l>יַּךְ</l><n>2</n> <s>H5221</s> <m>VhAmSM3</m> <E>Hirió<e> <E>de<e> <E>muerte<e> <E>a<e><q> <Q><l>כָּל־</l><n>3</n> <s>H3605</s> <m>NCACCC</m> <E>todos<e> <E>los<e><q> <Q><l>בְּכוֹר</l><n>4</n> <s>H1060</s> <m>NCcSMN</m> <E>primogénitos<e><q> <Q><l>בְּ</l><n>5</n> <m>PB</m> <E>en<e><q> <Q><l>ָם</l><n>7</n> <m>RBPM3</m> <E>su<e><q> <Q><l>אַרְצ</l><n>6</n> <s>H776</s> <m>NCcSFS</m> <E>tierra,<e> <E>Las<e><q> <Q><l>רֵאשִׁית</l><n>8</n> <s>H7225</s> <m>NCcSFN</m> <E>primicias<e><q> <Q><l>לְ</l><n>9</n> <m>PL</m> <E>de<e><q> <Q><l>כָל־</l><n>10</n> <s>H3605</s> <m>NCACCC</m> <E>toda<e><q> <Q><l>ָם</l><n>12</n> <m>RBPM3</m> <E>su<e><q> <Q><l>אוֹנ</l><n>11</n> <s>H202</s> <m>NCcSMS</m> <E>fuerza.<e><q>","tokens":[{"orig":"וַ","morphs":"Cc","num":"1","notrans":"s/t"},{"orig":"יַּךְ","strongs":"H5221","morphs":"VhAmSM3","es":["Hirió","de","muerte","a"],"num":"2"},{"orig":"כָּל־","strongs":"H3605","morphs":"NCACCC","es":["todos","los"],"num":"3"},{"orig":"בְּכוֹר","strongs":"H1060","morphs":"NCcSMN","es":"primogénitos","num":"4"},{"orig":"בְּ","morphs":"PB","es":"en","num":"5"},{"orig":"ָם","morphs":"RBPM3","es":"su","num":"7"},{"orig":"אַרְצ","strongs":"H776","morphs":"NCcSFS","es":["tierra,","Las"],"num":"6"},{"orig":"רֵאשִׁית","strongs":"H7225","morphs":"NCcSFN","es":"primicias","num":"8"},{"orig":"לְ","morphs":"PL","es":"de","num":"9"},{"orig":"כָל־","strongs":"H3605","morphs":"NCACCC","es":"toda","num":"10"},{"orig":"ָם","morphs":"RBPM3","es":"su","num":"12"},{"orig":"אוֹנ","strongs":"H202","morphs":"NCcSMS","es":"fuerza.","num":"11"}]},"37":{"raw":"<Q><l>וַ</l><n>1</n> <m>Cc</m> <z>s/t</z><q> <Q><l>ֵם</l><n>3</n> <m>RBPM3</m> <E>Los<e><q> <Q><l>יּוֹצִיא</l><n>2</n> <s>H3318</s> <m>VhAmSM3</m> <E>sacó<e><q> <Q><l>בְּ</l><n>4</n> <m>PB</m> <E>con<e><q> <Q><l>כֶסֶף</l><n>5</n> <s>H3701</s> <m>NCcSMN</m> <E>plata<e><q> <Q><l>וְ</l><n>6</n> <m>CC</m> <E>y<e><q> <Q><l>זָהָב</l><n>7</n> <s>H2091</s> <m>NCcSMN</m> <E>oro;<e><q> <Q><l>וְ</l><n>8</n> <m>CC</m> <E>Y<e><q> <Q><l>אֵין</l><n>9</n> <s>H369</s> <m>AQn</m> <E>no<e> <x><f> ← </f>hubo</x><q> <Q><l>בִּ</l><n>10</n> <m>PB</m> <E>en<e><q> <Q><l>ו</l><n>12</n> <m>RBSM3</m> <E>sus<e><q> <Q><l>שְׁבָטָי</l><n>11</n> <s>H7626</s> <m>NCcPMS</m> <E>tribus<e><q> <Q><l>כּוֹשֵׁל</l><n>13</n> <s>H3782</s> <m>VqAtSM-N</m> <E>enfermo.<e><q>","tokens":[{"orig":"וַ","morphs":"Cc","num":"1","notrans":"s/t"},{"orig":"ֵם","morphs":"RBPM3","es":"Los","num":"3"},{"orig":"יּוֹצִיא","strongs":"H3318","morphs":"VhAmSM3","es":"sacó","num":"2"},{"orig":"בְּ","morphs":"PB","es":"con","num":"4"},{"orig":"כֶסֶף","strongs":"H3701","morphs":"NCcSMN","es":"plata","num":"5"},{"orig":"וְ","morphs":"CC","es":"y","num":"6"},{"orig":"זָהָב","strongs":"H2091","morphs":"NCcSMN","es":"oro;","num":"7"},{"orig":"וְ","morphs":"CC","es":"Y","num":"8"},{"orig":"אֵין","strongs":"H369","morphs":"AQn","es":"no","num":"9","added":"← hubo","marks":"←"},{"orig":"בִּ","morphs":"PB","es":"en","num":"10"},{"orig":"ו","morphs":"RBSM3","es":"sus","num":"12"},{"orig":"שְׁבָטָי","strongs":"H7626","morphs":"NCcPMS","es":"tribus","num":"11"},{"orig":"כּוֹשֵׁל","strongs":"H3782","morphs":"VqAtSM-N","es":"enfermo.","num":"13"}]},"38":{"raw":"<Q><l>מִצְרַיִם</l><n>2</n> <s>H4714</s> <m>NPLSFN</m> <E>Egipto<e> <x><f>→</f>se</x><q> <Q><l>שָׂמַח</l><n>1</n> <s>H8055</s> <m>VqAsSM3</m> <E>alegró<e><q> <Q><l>בְּ</l><n>3</n> <m>PB</m> <E>de<e> <E>que<e> <f>‹</f><q><Q><l>צֵאת</l><n>4</n> <l>ָם</l><n>5</n> <f>›</f><s>H3318</s> <m>VqAT---S</m><m>,</m> <m>RBPM3</m> <E>salieran,<e><q> <Q><l>כִּי־</l><n>6</n> <s>H3588</s> <m>CK</m> <E>Porque<e><q> <Q><l>ָם</l><n>9</n> <m>RBPM3</m> <E>su<e><q> <Q><l>פַּחְדּ</l><n>8</n> <s>H6343</s> <m>NCcSMS</m> <E>terror<e> <x><f>→</f>había</x><q> <Q><l>נָפַל</l><n>7</n> <s>H5307</s> <m>VqAsSM3</m> <E>caído<e><q> <Q><l>עֲלֵי</l><n>10</n> <s>H5921</s> <m>Pu</m> <E>sobre<e><q> <Q><l>הֶם</l><n>11</n> <m>RBPM3</m> <E>ellos.<e><q>","tokens":[{"orig":"מִצְרַיִם","strongs":"H4714","morphs":"NPLSFN","es":"Egipto","num":"2","added":"→se","marks":"→"},{"orig":"שָׂמַח","strongs":"H8055","morphs":"VqAsSM3","es":"alegró","num":"1"},{"orig":"בְּ","morphs":"PB","es":["de","que"],"num":"3","marks":"‹"},{"orig":["צֵאת","ָם"],"strongs":"H3318","morphs":["VqAT---S",",","RBPM3"],"es":"salieran,","num":["4","5"],"marks":"›"},{"orig":"כִּי־","strongs":"H3588","morphs":"CK","es":"Porque","num":"6"},{"orig":"ָם","morphs":"RBPM3","es":"su","num":"9"},{"orig":"פַּחְדּ","strongs":"H6343","morphs":"NCcSMS","es":"terror","num":"8","added":"→había","marks":"→"},{"orig":"נָפַל","strongs":"H5307","morphs":"VqAsSM3","es":"caído","num":"7"},{"orig":"עֲלֵי","strongs":"H5921","morphs":"Pu","es":"sobre","num":"10"},{"orig":"הֶם","morphs":"RBPM3","es":"ellos.","num":"11"}]},"39":{"raw":"<Q><l>פָּרַשׂ</l><n>1</n> <s>H6566</s> <m>VqAsSM3</m> <E>Extendió<e> <E>una<e><q> <Q><l>עָנָן</l><n>2</n> <s>H6051</s> <m>NCcSMN</m> <E>nube<e><q> <Q><l>לְ</l><n>3</n> <m>PL</m> <E>por<e><q> <Q><l>מָסָךְ</l><n>4</n> <s>H4539</s> <m>NCcSMN</m> <E>cubierta,<e><q> <Q><l>וְ</l><n>5</n> <m>CC</m> <E>Y<e><q> <Q><l>אֵשׁ</l><n>6</n> <s>H784</s> <m>NCcSFN</m> <E>fuego<e><q> <Q><l>לְ</l><n>7</n> <m>PL</m> <E>para<e><q> <Q><l>הָאִיר</l><n>8</n> <s>H215</s> <m>VhAT---C</m> <E>alumbrar<e> <E>la<e><q> <Q><l>לָיְלָה</l><n>9</n> <s>H3915</s> <m>NCcSMP</m> <E>noche.<e><q>","tokens":[{"orig":"פָּרַשׂ","strongs":"H6566","morphs":"VqAsSM3","es":["Extendió","una"],"num":"1"},{"orig":"עָנָן","strongs":"H6051","morphs":"NCcSMN","es":"nube","num":"2"},{"orig":"לְ","morphs":"PL","es":"por","num":"3"},{"orig":"מָסָךְ","strongs":"H4539","morphs":"NCcSMN","es":"cubierta,","num":"4"},{"orig":"וְ","morphs":"CC","es":"Y","num":"5"},{"orig":"אֵשׁ","strongs":"H784","morphs":"NCcSFN","es":"fuego","num":"6"},{"orig":"לְ","morphs":"PL","es":"para","num":"7"},{"orig":"הָאִיר","strongs":"H215","morphs":"VhAT---C","es":["alumbrar","la"],"num":"8"},{"orig":"לָיְלָה","strongs":"H3915","morphs":"NCcSMP","es":"noche.","num":"9"}]},"40":{"raw":"<Q><l>שָׁאַל</l><n>1</n> <s>H7592</s> <m>VqAsSM3</m> <E>Pidieron,<e><q> <Q><l>וַ</l><n>2</n> <m>Cc</m> <E>e<e> <x><f>→</f>hizo</x><q> <Q><l>יָּבֵא</l><n>3</n> <s>H935</s> <m>VhAmSM3</m> <E>venir<e><q> <Q><l>שְׂלָו</l><n>4</n> <s>H7958</s> <m>NCcSMN</m> <E>codornices;<e><q> <Q><l>וְ</l><n>5</n> <m>CC</m> <E>Y<e><q> <Q><l>ֵם</l><n>9</n> <m>RBPM3</m> <E>los<e><q> <Q><l>יַשְׂבִּיע</l><n>8</n> <s>H7646</s> <m>VhAPSM3</m> <E>sació<e> <E>de<e><q> <Q><l>לֶחֶם</l><n>6</n> <s>H3899</s> <m>NCcSMC</m> <E>pan<e> <x><f> ← </f>del</x><q> <Q><l>שָׁמַיִם</l><n>7</n> <s>H8064</s> <m>NCcDMN</m> <E>cielo.<e><q>","tokens":[{"orig":"שָׁאַל","strongs":"H7592","morphs":"VqAsSM3","es":"Pidieron,","num":"1"},{"orig":"וַ","morphs":"Cc","es":"e","num":"2","added":"→hizo","marks":"→"},{"orig":"יָּבֵא","strongs":"H935","morphs":"VhAmSM3","es":"venir","num":"3"},{"orig":"שְׂלָו","strongs":"H7958","morphs":"NCcSMN","es":"codornices;","num":"4"},{"orig":"וְ","morphs":"CC","es":"Y","num":"5"},{"orig":"ֵם","morphs":"RBPM3","es":"los","num":"9"},{"orig":"יַשְׂבִּיע","strongs":"H7646","morphs":"VhAPSM3","es":["sació","de"],"num":"8"},{"orig":"לֶחֶם","strongs":"H3899","morphs":"NCcSMC","es":"pan","num":"6","added":"← del","marks":"←"},{"orig":"שָׁמַיִם","strongs":"H8064","morphs":"NCcDMN","es":"cielo.","num":"7"}]},"41":{"raw":"<Q><l>פָּתַח</l><n>1</n> <s>H6605</s> <m>VqAsSM3</m> <E>Abrió<e> <E>la<e><q> <Q><l>צוּר</l><n>2</n> <s>H6697</s> <m>NCcSMN</m> <E>peña,<e><q> <Q><l>וַ</l><n>3</n> <m>Cc</m> <E>y<e><q> <Q><l>יָּזוּבוּ</l><n>4</n> <s>H2100</s> <m>VqAmPM3</m> <E>fluyeron<e><q> <Q><l>מָיִם</l><n>5</n> <s>H4325</s> <m>NCcDMP</m> <E>aguas;<e><q> <Q><l>הָלְכוּ</l><n>6</n> <s>H1980</s> <m>VqAsPC3</m> <E>Corrieron<e><q> <Q><l>בּ</l><n>7</n> <m>PB</m> <E>por<e><q> <Q><l>ַ</l><n>8</n> <m>XD</m> <E>los<e><q> <Q><l>צִּיּוֹת</l><n>9</n> <s>H6723</s> <m>NCcPFNh</m> <E>sequedales<e> <E>como<e> <E>un<e><q> <Q><l>נָהָר</l><n>10</n> <s>H5104</s> <m>NCcSMN</m> <E>río.<e><q>","tokens":[{"orig":"פָּתַח","strongs":"H6605","morphs":"VqAsSM3","es":["Abrió","la"],"num":"1"},{"orig":"צוּר","strongs":"H6697","morphs":"NCcSMN","es":"peña,","num":"2"},{"orig":"וַ","morphs":"Cc","es":"y","num":"3"},{"orig":"יָּזוּבוּ","strongs":"H2100","morphs":"VqAmPM3","es":"fluyeron","num":"4"},{"orig":"מָיִם","strongs":"H4325","morphs":"NCcDMP","es":"aguas;","num":"5"},{"orig":"הָלְכוּ","strongs":"H1980","morphs":"VqAsPC3","es":"Corrieron","num":"6"},{"orig":"בּ","morphs":"PB","es":"por","num":"7"},{"orig":"ַ","morphs":"XD","num":"8","notrans":"s/t"},{"orig":"צִּיּוֹת","strongs":"H6723","morphs":"NCcPFNh","es":["sequedales","como","un"],"num":"9"},{"orig":"נָהָר","strongs":"H5104","morphs":"NCcSMN","es":"río.","num":"10"}]},"42":{"raw":"<Q><l>כִּי־</l><n>1</n> <s>H3588</s> <m>CK</m> <E>Porque<e> <x><f>→</f>se</x><q> <Q><l>זָכַר</l><n>2</n> <s>H2142</s> <m>VqAsSM3</m> <E>acordó<e><q> <Q><l>אֶת־</l><n>3</n> <s>H853</s> <m>PA</m> <E>de<e><q> <Q><l>ֹו</l><n>6</n> <m>RBSM3</m> <E>su<e><q> <Q><l>קָדְשׁ</l><n>5</n> <s>H6944</s> <m>NCcSMS</m> <E>santa<e><q> <Q><l>דְּבַר</l><n>4</n> <s>H1697</s> <m>NCcSMC</m> <E>palabra<e> <E>Dada<e><q> <Q><l>אֶת־</l><n>7</n> <s>H853</s> <m>PA</m> <E>a<e><q> <Q><l>אַבְרָהָם</l><n>8</n> <s>H85</s> <m>NPHSMN</m> <E>Abraham<e><q> <Q><l>ֹו</l><n>10</n> <m>RBSM3</m> <E>su<e><q> <Q><l>עַבְדּ</l><n>9</n> <s>H5650</s> <m>NCcSMS</m> <E>siervo.<e><q>","tokens":[{"orig":"כִּי־","strongs":"H3588","morphs":"CK","es":"Porque","num":"1","added":"→se","marks":"→"},{"orig":"זָכַר","strongs":"H2142","morphs":"VqAsSM3","es":"acordó","num":"2"},{"orig":"אֶת־","strongs":"H853","morphs":"PA","es":"de","num":"3"},{"orig":"ֹו","morphs":"RBSM3","es":"su","num":"6"},{"orig":"קָדְשׁ","strongs":"H6944","morphs":"NCcSMS","es":"santa","num":"5"},{"orig":"דְּבַר","strongs":"H1697","morphs":"NCcSMC","es":["palabra","Dada"],"num":"4"},{"orig":"אֶת־","strongs":"H853","morphs":"PA","es":"a","num":"7"},{"orig":"אַבְרָהָם","strongs":"H85","morphs":"NPHSMN","es":"Abraham","num":"8"},{"orig":"ֹו","morphs":"RBSM3","es":"su","num":"10"},{"orig":"עַבְדּ","strongs":"H5650","morphs":"NCcSMS","es":"siervo.","num":"9"}]},"43":{"raw":"<Q><l>וַ</l><n>1</n> <m>Cc</m> <z>s/t</z><q> <Q><l>יּוֹצִא</l><n>2</n> <s>H3318</s> <m>VhAmSM3</m> <E>Sacó<e> <E>a<e><q> <Q><l>ֹו</l><n>4</n> <m>RBSM3</m> <E>su<e><q> <Q><l>עַמּ</l><n>3</n> <s>H5971</s> <m>NCcSMS</m> <E>pueblo<e><q> <Q><l>בְ</l><n>5</n> <m>PB</m> <E>con<e><q> <Q><l>שָׂשׂוֹן</l><n>6</n> <s>H8342</s> <m>NCcSMN</m> <E>gozo;<e><q> <Q><l>בְּ</l><n>7</n> <m>PB</m> <E>Con<e><q> <Q><l>רִנָּה</l><n>8</n> <s>H7440</s> <m>NCcSFN</m> <E>júbilo<e><q> <Q><l>אֶת־</l><n>9</n> <s>H853</s> <m>PA</m> <E>a<e><q> <Q><l>ו</l><n>11</n> <m>RBSM3</m> <E>sus<e><q> <Q><l>בְּחִירָי</l><n>10</n> <s>H972</s> <m>NCcPMS</m> <E>escogidos.<e><q>","tokens":[{"orig":"וַ","morphs":"Cc","num":"1","notrans":"s/t"},{"orig":"יּוֹצִא","strongs":"H3318","morphs":"VhAmSM3","es":["Sacó","a"],"num":"2"},{"orig":"ֹו","morphs":"RBSM3","es":"su","num":"4"},{"orig":"עַמּ","strongs":"H5971","morphs":"NCcSMS","es":"pueblo","num":"3"},{"orig":"בְ","morphs":"PB","es":"con","num":"5"},{"orig":"שָׂשׂוֹן","strongs":"H8342","morphs":"NCcSMN","es":"gozo;","num":"6"},{"orig":"בְּ","morphs":"PB","es":"Con","num":"7"},{"orig":"רִנָּה","strongs":"H7440","morphs":"NCcSFN","es":"júbilo","num":"8"},{"orig":"אֶת־","strongs":"H853","morphs":"PA","es":"a","num":"9"},{"orig":"ו","morphs":"RBSM3","es":"sus","num":"11"},{"orig":"בְּחִירָי","strongs":"H972","morphs":"NCcPMS","es":"escogidos.","num":"10"}]},"44":{"raw":"<Q><l>וַ</l><n>1</n> <m>Cc</m> <z>s/t</z> <f>‹</f><q><Q><l>לָ</l><n>3</n> <l>הֶם</l><n>4</n> <f>›</f><s>H1992</s> <m>PL</m><m>,</m> <m>RBPM3</m> <E>Les<e><q> <Q><l>יִּתֵּן</l><n>2</n> <s>H5414</s> <m>VqAmSM3</m> <E>dio<e> <x><f>→</f>las</x><q> <Q><l>אַרְצוֹת</l><n>5</n> <s>H776</s> <m>NCcPFC</m> <E>tierras<e> <x><f> ← </f>de</x> <E>las<e><q> <Q><l>גּוֹיִם</l><n>6</n> <s>H1471</s> <m>NCcPMN</m> <E>naciones,<e><q> <Q><l>וַ</l><n>7</n> <m>CC</m> <E>Y<e> <x><f>→</f>las</x><q> <Q><l>עֲמַל</l><n>8</n> <s>H5999</s> <m>NCcSMC</m> <E>labores<e> <x><f> ← </f>de</x> <E>los<e><q> <Q><l>לְאֻמִּים</l><n>9</n> <s>H3817</s> <m>NCcPMN</m> <E>pueblos<e><q> <Q><l>יִירָשׁוּ</l><n>10</n> <s>H3423</s> <m>VqAMPM3</m> <E>heredaron;<e><q>","tokens":[{"orig":"וַ","morphs":"Cc","num":"1","notrans":"s/t","marks":"‹"},{"orig":["לָ","הֶם"],"strongs":"H1992","morphs":["PL",",","RBPM3"],"es":"Les","num":["3","4"],"marks":"›"},{"orig":"יִּתֵּן","strongs":"H5414","morphs":"VqAmSM3","es":"dio","num":"2","added":"→las","marks":"→"},{"orig":"אַרְצוֹת","strongs":"H776","morphs":"NCcPFC","es":["tierras","las"],"num":"5","added":"← de","marks":"←"},{"orig":"גּוֹיִם","strongs":"H1471","morphs":"NCcPMN","es":"naciones,","num":"6"},{"orig":"וַ","morphs":"CC","es":"Y","num":"7","added":"→las","marks":"→"},{"orig":"עֲמַל","strongs":"H5999","morphs":"NCcSMC","es":["labores","los"],"num":"8","added":"← de","marks":"←"},{"orig":"לְאֻמִּים","strongs":"H3817","morphs":"NCcPMN","es":"pueblos","num":"9"},{"orig":"יִירָשׁוּ","strongs":"H3423","morphs":"VqAMPM3","es":"heredaron;","num":"10"}]},"45":{"raw":"<Q><l>בַּעֲבוּר</l><n>1</n> <m>CX</m><E>Para<e> <x><f> ← </f>que</x><q> <Q><l>יִשְׁמְרוּ</l><n>2</n> <s>H8104</s> <m>VqAMPM3</m> <E>guardasen<e><q> <Q><l>ו</l><n>4</n> <m>RBSM3</m> <E>sus<e><q> <Q><l>חֻקָּי</l><n>3</n> <s>H2706</s> <m>NCcPMS</m> <E>estatutos,<e><q> <Q><l>וְ</l><n>5</n> <m>CC</m> <E>Y<e><q> <Q><l>יִנְצֹרוּ</l><n>8</n> <s>H5341</s> <m>VqAMPM3</m> <E>cumpliesen<e><q> <Q><l>ו</l><n>7</n> <m>RBSM3</m> <E>sus<e><q> <Q><l>תוֹרֹתָי</l><n>6</n> <s>H8451</s> <m>NCcPFS</m> <E>leyes.<e> <f>‹</f><q><Q><l>הַלְלוּ־</l><n>9</n> <l>יָהּ</l><n>10</n> <f>›</f><s>H3050</s> <m>VpAIPM2</m><m>,</m> <m>NPDSMN</m> <E>Aleluya.<e><q>","tokens":[{"orig":"בַּעֲבוּר","morphs":"CX","es":"Para","num":"1","added":"← que","marks":"←"},{"orig":"יִשְׁמְרוּ","strongs":"H8104","morphs":"VqAMPM3","es":"guardasen","num":"2"},{"orig":"ו","morphs":"RBSM3","es":"sus","num":"4"},{"orig":"חֻקָּי","strongs":"H2706","morphs":"NCcPMS","es":"estatutos,","num":"3"},{"orig":"וְ","morphs":"CC","es":"Y","num":"5"},{"orig":"יִנְצֹרוּ","strongs":"H5341","morphs":"VqAMPM3","es":"cumpliesen","num":"8"},{"orig":"ו","morphs":"RBSM3","es":"sus","num":"7"},{"orig":"תוֹרֹתָי","strongs":"H8451","morphs":"NCcPFS","es":"leyes.","num":"6","marks":"‹"},{"orig":["הַלְלוּ־","יָהּ"],"strongs":"H3050","morphs":["VpAIPM2",",","NPDSMN"],"es":"Aleluya.","num":["9","10"],"marks":"›"}]}}
