{"1":{"forms":["וַ֠","יִּשְׁלַח","חירם","i>(חוּרָ֨ם","מֶֽלֶךְ","־צֹ֥ר","מַלְאָכִים֮","אֶל","־דָּוִיד֒","וַ","עֲצֵ֣י","אֲרָזִ֔ים","וְ","חָרָשֵׁ֣י","קִ֔יר","וְ","חָרָשֵׁ֖י","עֵצִ֑ים","לִ","בְנ֥וֹת","בָּֽיִת"],"morphs":["CONJ","VERBO.QAL.WAYYIQT.P3.M.SG","NPROP","NPROP","SUBS.M.SG.C","NPROP","SUBS.M.PL.A","PREP","NPROP","CONJ","SUBS.M.PL.C","SUBS.M.PL.A","CONJ","SUBS.M.PL.C","SUBS.M.SG.A","CONJ","SUBS.M.PL.C","SUBS.M.PL.A","PREP","VERBO.QAL.INFC","SUBS.M.SG.A"]},"2":{"forms":["וַ","יֵּ֣דַע","דָּוִ֔יד","כִּֽי","־הֱכִינ֧","וֹ","יְהוָ֛ה","לְ","מֶ֖לֶךְ","עַל","־יִשְׂרָאֵ֑ל","כִּֽי","־נִשֵּׂ֤את","לְ","מַ֨עְלָ","ה֙","מַלְכוּת֔","וֹ","בַּ","עֲב֖וּר","עַמּ֥","וֹ","יִשְׂרָאֵֽל"],"morphs":["CONJ","VERBO.QAL.WAYYIQT.P3.M.SG","NPROP","CONJ","VERBO.HIF.PERF.P3.M.SG","PRS.P3.M.SG","NPROP","PREP","SUBS.M.SG.A","PREP","NPROP","CONJ","VERBO.NIF.PERF.P3.F.SG","PREP","ADV","SUF.DIR.HE","SUBS.F.SG.C","PRS.P3.M.SG","PREP","SUBS.M.SG.C","SUBS.M.SG.C","PRS.P3.M.SG","NPROP"]},"3":{"forms":["וַ","יִּקַּ֨ח","דָּוִ֥יד","ע֛וֹד","נָשִׁ֖ים","בִּ","ירוּשָׁלִָ֑ם","וַ","יּ֧וֹלֶד","דָּוִ֛יד","ע֖וֹד","בָּנִ֥ים","וּ","בָנֽוֹת"],"morphs":["CONJ","VERBO.QAL.WAYYIQT.P3.M.SG","NPROP","ADV","SUBS.F.PL.A","PREP","NPROP","CONJ","VERBO.HIF.WAYYIQT.P3.M.SG","NPROP","ADV","SUBS.M.PL.A","CONJ","SUBS.F.PL.A"]},"4":{"forms":["וְ","אֵ֨לֶּה֙","שְׁמ֣וֹת","הַ","יְלוּדִ֔ים","אֲשֶׁ֥ר","הָיוּ","בִּ","ירוּשָׁלִָ֑ם","שַׁמּ֣וּעַ","וְ","שׁוֹבָ֔ב","נָתָ֖ן","וּ","שְׁלֹמֹֽה"],"morphs":["CONJ","PRON.DEM.COMMON.PL","SUBS.M.PL.C","ART","VERBO.QAL.PTCP.M.PL.A","REL","VERBO.QAL.PERF.P3.COMMON.PL","PREP","NPROP","NPROP","CONJ","NPROP","NPROP","CONJ","NPROP"]},"5":{"forms":["וְ","יִבְחָ֥ר","וֶ","אֱלִישׁ֖וּעַ","וְ","אֶלְפָּֽלֶט"],"morphs":["CONJ","NPROP","CONJ","NPROP","CONJ","NPROP"]},"6":{"forms":["וְ","נֹ֥גַהּ","וְ","נֶ֖פֶג","וְ","יָפִֽיעַ"],"morphs":["CONJ","NPROP","CONJ","NPROP","CONJ","NPROP"]},"7":{"forms":["וֶ","אֱלִישָׁמָ֥ע","וּ","בְעֶלְיָדָ֖ע","וֶ","אֱלִיפָֽלֶט"],"morphs":["CONJ","NPROP","CONJ","NPROP","CONJ","NPROP"]},"8":{"forms":["וַ","יִּשְׁמְע֣וּ","פְלִשְׁתִּ֗ים","כִּי","־נִמְשַׁ֨ח","דָּוִ֤יד","לְ","מֶ֨לֶךְ֙","עַל","־כָּל","־יִשְׂרָאֵ֔ל","וַ","יַּעֲל֥וּ","כָל","־פְּלִשְׁתִּ֖ים","לְ","בַקֵּ֣שׁ","אֶת","־דָּוִ֑יד","וַ","יִּשְׁמַ֣ע","דָּוִ֔יד","וַ","יֵּצֵ֖א","לִ","פְנֵי","הֶֽם"],"morphs":["CONJ","VERBO.QAL.WAYYIQT.P3.M.PL","GENT.M.PL.A","CONJ","VERBO.NIF.PERF.P3.M.SG","NPROP","PREP","SUBS.M.SG.A","PREP","SUBS.M.SG.C","NPROP","CONJ","VERBO.QAL.WAYYIQT.P3.M.PL","SUBS.M.SG.C","GENT.M.PL.A","PREP","VERBO.PIEL.INFC","PART.OBJ.DIR","NPROP","CONJ","VERBO.QAL.WAYYIQT.P3.M.SG","NPROP","CONJ","VERBO.QAL.WAYYIQT.P3.M.SG","PREP","SUBS.BOTH.PL.C","PRS.P3.M.PL"]},"9":{"forms":["וּ","פְלִשְׁתִּ֖ים","בָּ֑אוּ","וַֽ","יִּפְשְׁט֖וּ","בְּ","עֵ֥מֶק","רְפָאִֽים"],"morphs":["CONJ","GENT.M.PL.A","VERBO.QAL.PERF.P3.COMMON.PL","CONJ","VERBO.QAL.WAYYIQT.P3.M.PL","PREP","SUBS.M.SG.C","NPROP"]},"10":{"forms":["וַ","יִּשְׁאַ֨ל","דָּוִ֤יד","בֵּ","אלֹהִים֙","לֵ","אמֹ֔ר","הַ","אֶֽעֱלֶה֙","עַל","־פלשתיים","i>(פְּלִשְׁתִּ֔ים","וּ","נְתַתָּ֖","ם","בְּ","יָדִ֑","י","וַ","יֹּ֨אמֶר","יְהוָה֙","עֲלֵ֔ה","וּ","נְתַתִּ֖י","ם","בְּ","יָדֶֽ","ךָ"],"morphs":["CONJ","VERBO.QAL.WAYYIQT.P3.M.SG","NPROP","PREP","SUBS.M.PL.A","PREP","VERBO.QAL.INFC","PART.INTERR","VERBO.QAL.IMPF.P1.COMMON.SG","PREP","GENT.M.PL.A","GENT.M.PL.A","CONJ","VERBO.QAL.SEQ.PERF.P2.M.SG","PRS.P3.M.PL","PREP","SUBS.BOTH.SG.C","PRS.P1.COMMON.SG","CONJ","VERBO.QAL.WAYYIQT.P3.M.SG","NPROP","VERBO.QAL.IMPV.P2.M.SG","CONJ","VERBO.QAL.SEQ.PERF.P1.COMMON.SG","PRS.P3.M.PL","PREP","SUBS.BOTH.SG.C","PRS.P2.M.SG"]},"11":{"forms":["וַ","יַּעֲל֥וּ","בְּ","בַֽעַל","־פְּרָצִים֮","וַ","יַּכֵּ֣","ם","שָׁ֣ם","דָּוִיד֒","וַ","יֹּ֣אמֶר","דָּוִ֔יד","פָּרַ֨ץ","הָֽ","אֱלֹהִ֧ים","אֶת","־אוֹיְבַ֛","י","בְּ","יָדִ֖","י","כְּ","פֶ֣רֶץ","מָ֑יִם","עַל","־כֵּ֗ן","קָֽרְא֛וּ","שֵֽׁם","־הַ","מָּק֥וֹם","הַ","ה֖וּא","בַּ֥עַל","פְּרָצִֽים"],"morphs":["CONJ","VERBO.QAL.WAYYIQT.P3.M.PL","PREP","NPROP","NPROP","CONJ","VERBO.HIF.WAYYIQT.P3.M.SG","PRS.P3.M.PL","ADV","NPROP","CONJ","VERBO.QAL.WAYYIQT.P3.M.SG","NPROP","VERBO.QAL.PERF.P3.M.SG","ART","SUBS.M.PL.A","PART.OBJ.DIR","VERBO.QAL.PTCA.M.PL.C","PRS.P1.COMMON.SG","PREP","SUBS.BOTH.SG.C","PRS.P1.COMMON.SG","PREP","SUBS.M.SG.C","SUBS.M.PL.A","PREP","PART.DEM","VERBO.QAL.PERF.P3.COMMON.PL","SUBS.M.SG.C","ART","SUBS.M.SG.A","ART","PRON.PERS.P3.M.SG","NPROP","NPROP"]},"12":{"forms":["וַ","יַּעַזְבוּ","־שָׁ֖ם","אֶת","־אֱלֹֽהֵי","הֶ֑ם","וַ","יֹּ֣אמֶר","דָּוִ֔יד","וַ","יִּשָּׂרְפ֖וּ","בָּ","אֵֽשׁ"],"morphs":["CONJ","VERBO.QAL.WAYYIQT.P3.M.PL","ADV","PART.OBJ.DIR","SUBS.M.PL.C","PRS.P3.M.PL","CONJ","VERBO.QAL.WAYYIQT.P3.M.SG","NPROP","CONJ","VERBO.NIF.WAYYIQT.P3.M.PL","PREP","SUBS.BOTH.SG.A"]},"13":{"forms":["וַ","יֹּסִ֤יפוּ","עוֹד֙","פְּלִשְׁתִּ֔ים","וַֽ","יִּפְשְׁט֖וּ","בָּ","עֵֽמֶק"],"morphs":["CONJ","VERBO.HIF.WAYYIQT.P3.M.PL","ADV","GENT.M.PL.A","CONJ","VERBO.QAL.WAYYIQT.P3.M.PL","PREP","SUBS.M.SG.A"]},"14":{"forms":["וַ","יִּשְׁאַ֨ל","ע֤וֹד","דָּוִיד֙","בֵּֽ","אלֹהִ֔ים","וַ","יֹּ֤אמֶר","הָֽ","אֱלֹהִ֔ים","לֹ֥א","תַֽעֲלֶ֖ה","אַֽחֲרֵי","הֶ֑ם","הָסֵב֙","מֵֽ","עֲלֵי","הֶ֔ם","וּ","בָ֥אתָ","מִ","מּ֥וּל","הַ","בְּכָאִֽים"],"morphs":["CONJ","VERBO.QAL.WAYYIQT.P3.M.SG","ADV","NPROP","PREP","SUBS.M.PL.A","CONJ","VERBO.QAL.WAYYIQT.P3.M.SG","ART","SUBS.M.PL.A","NEG","VERBO.QAL.IMPF.P2.M.SG","PREP","PRS.P3.M.PL","VERBO.HIF.IMPV.P2.M.SG","PREP","PREP","PRS.P3.M.PL","CONJ","VERBO.QAL.SEQ.PERF.P2.M.SG","PREP","PREP","ART","SUBS.M.PL.A"]},"15":{"forms":["וִ֠","יהִי","כְּֽ","שָׁמְעֲ","ךָ֞","אֶת","־ק֤וֹל","הַ","צְּעָדָה֙","בְּ","רָאשֵׁ֣י","הַ","בְּכָאִ֔ים","אָ֖ז","תֵּצֵ֣א","בַ","מִּלְחָמָ֑ה","כִּֽי","־יָצָ֤א","הָֽ","אֱלֹהִים֙","לְ","פָנֶ֔י","ךָ","לְ","הַכּ֖וֹת","אֶת","־מַחֲנֵ֥ה","פְלִשְׁתִּֽים"],"morphs":["CONJ","VERBO.QAL.JUSS.P3.M.SG","PREP","VERBO.QAL.INFC","PRS.P2.M.SG","PART.OBJ.DIR","SUBS.M.SG.C","ART","SUBS.F.SG.A","PREP","SUBS.M.PL.C","ART","SUBS.M.PL.A","ADV","VERBO.QAL.IMPF.P2.M.SG","PREP","SUBS.F.SG.A","CONJ","VERBO.QAL.PERF.P3.M.SG","ART","SUBS.M.PL.A","PREP","SUBS.BOTH.PL.C","PRS.P2.M.SG","PREP","VERBO.HIF.INFC","PART.OBJ.DIR","SUBS.BOTH.SG.C","GENT.M.PL.A"]},"16":{"forms":["וַ","יַּ֣עַשׂ","דָּוִ֔יד","כַּֽ","אֲשֶׁ֥ר","צִוָּ֖","הוּ","הָֽ","אֱלֹהִ֑ים","וַ","יַּכּוּ֙","אֶת","־מַחֲנֵ֣ה","פְלִשְׁתִּ֔ים","מִ","גִּבְע֖וֹן","וְ","עַד","־גָּֽזְרָ","ה"],"morphs":["CONJ","VERBO.QAL.WAYYIQT.P3.M.SG","NPROP","PREP","REL","VERBO.PIEL.PERF.P3.M.SG","PRS.P3.M.SG","ART","SUBS.M.PL.A","CONJ","VERBO.HIF.WAYYIQT.P3.M.PL","PART.OBJ.DIR","SUBS.BOTH.SG.C","GENT.M.PL.A","PREP","NPROP","CONJ","PREP","NPROP","SUF.DIR.HE"]},"17":{"forms":["וַ","יֵּצֵ֥א","שֵׁם","־דָּוִ֖יד","בְּ","כָל","־הָֽ","אֲרָצ֑וֹת","וַֽ","יהוָ֛ה","נָתַ֥ן","אֶת","־פַּחְדּ֖","וֹ","עַל","־כָּל","־הַ","גּוֹיִֽם"],"morphs":["CONJ","VERBO.QAL.WAYYIQT.P3.M.SG","SUBS.M.SG.C","NPROP","PREP","SUBS.M.SG.C","ART","SUBS.BOTH.PL.A","CONJ","NPROP","VERBO.QAL.PERF.P3.M.SG","PART.OBJ.DIR","SUBS.M.SG.C","PRS.P3.M.SG","PREP","SUBS.M.SG.C","ART","SUBS.M.PL.A"]}}